Workbook
Name Produtos: '📋 Catálogo'!$B$7:$B$39

Sheet 📑 Índice
A1: Taldo Studio 3D — Gestão v7.3
A2: Impressão 3D · @TaldoStudio3d · Av. Sebastião Henriques, 575
A4: FLUXO DO DIA A DIA
A5: 1 | B5: 🧾 Romaneio | C5: Montar orçamento/pedido
A6: 2 | B6: 📦 Pedidos | C6: Registrar pedido confirmado
A7: 3 | B7: 🖨️ Produção | C7: Ver o que fabricar
A8: 4 | B8: 📦 Est. Peças | C8: Atualizar peças prontas
A9: 5 | B9: 🎨 Filamento | C9: Registrar uso de filamento
A10: 6 | B10: 💳 Lançamentos | C10: Compras parceladas do cartão
A12: TODAS AS ABAS
A13: ⚙️ Parâmetros | B13: Custos e categorias
A14: 📋 Catálogo | B14: Produtos e preços
A15: 🎨 Filamento | B15: Estoque de filamento
A16: 🧾 Romaneio | B16: Montar pedido
A17: 📦 Pedidos | B17: Histórico
A18: 🖨️ Produção | B18: Fila de fabricação
A19: 📦 Est. Peças | B19: Peças prontas
A20: 🔧 Manutenção | B20: Horas das máquinas
A21: 🏪 Consignados | B21: Bancas
A22: 📊 Relatório | B22: Indicadores
A23: 💳 Lançamentos | B23: Parcelas do cartão
A24: 📅 Proj. Mensal | B24: Gastos por mês
A25: 📊 Resumo Parcelas | B25: Resumo financeiro
A28: REGRAS IMPORTANTES
A29: 💳 UMA linha por compra — atualize Parc. Atual, não crie linha nova cada mês.
A30: 💳 Data na Fatura = quando a parcela aparece no cartão (branco = mês atual).
A31: 💳 Status "Cancelado" remove da projeção mensal.
A32: 🧾 Cadastre o produto no Catálogo antes de usar no Romaneio.
A33: 🎨 Registre Saídas de filamento após cada impressão.

Sheet ⚙️ Parâmetros
B1: Taldo Studio 3D · Impressão 3D Personalizada · @TaldoStudio3d · Av. Sebastião Henriques, 575
A4: ⚙️ PARÂMETROS DE CUSTO
A5: PARÂMETRO | B5: VALOR | C5: UNIDADE | D5: OBSERVAÇÃO
A6: Custo filamento | B6: 100 | C6: R$/kg | D6: Padrão geral
A7: Consumo máquina | B7: 0.15 | C7: kW/h | D7: Por hora
A8: Tarifa energia | B8: 0.9 | C8: R$/kWh | D8: Verificar conta
A9: Desgaste máquina | B9: 2 | C9: R$/h | D9: Reserva manutenção
A10: Embalagem | B10: 0.07 | C10: R$/peça | D10: Sempre aplicar
A11: Argola chaveiro | B11: 0.15 | C11: R$/un | D11: Se for chaveiro
A12: Ímã | B12: 0.13 | C12: R$/un | D12: Se tiver ímã
A13: Mult. Varejo | B13: 3.5 | C13: × | D13: Pessoa física / unitário
A14: Mult. Atacado | B14: 2.5 | C14: × | D14: Revendedor / volume
A15: % Reserva manutenção | B15: 0.1 | C15: % | D15: Sobre receita
A16: Nº máquinas ativas | B16: 2 | C16: un | D16: Atualizar ao comprar
A19: 🏷️ CATEGORIAS / SKU
A20: CATEGORIA | B20: CÓDIGO | C20: EXEMPLO | D20: PALAVRAS-CHAVE
A21: Chaveiro | B21: CH | C21: CH-2026-001 | D21: chaveiro,chave,keychain
A22: Caixinha | B22: CX | C22: CX-2026-002 | D22: caixa,caixinha,estojo
A23: Miniatura | B23: MN | C23: MN-2026-003 | D23: miniatura,boneco,figura,polvo,stitch
A24: Troféu | B24: TR | C24: TR-2026-004 | D24: trofeu,troféu,premio,medalha
A25: Plaquinha | B25: PQ | C25: PQ-2026-005 | D25: plaquinha,placa,letreiro
A26: Porta-retrato | B26: PR | C26: PR-2026-006 | D26: porta-retrato,moldura,frame
A27: Enfeite/Decoração | B27: EN | C27: EN-2026-007 | D27: enfeite,decoração,ornamento
A28: Peça Técnica | B28: PT | C28: PT-2026-008 | D28: peca,peça,suporte,adaptador
A29: Ímã de Geladeira | B29: IM | C29: IM-2026-009 | D29: ima,ímã,geladeira,magnet
A30: Kit / Combo | B30: KT | C30: KT-2026-010 | D30: kit,combo,conjunto,pack

Sheet 📋 Catálogo
B1: Taldo Studio 3D · Impressão 3D Personalizada · @TaldoStudio3d · Av. Sebastião Henriques, 575
A4: 📋 CATÁLOGO — Cadastre aqui cada produto com todas as informações. O Romaneio vai puxar tudo daqui.
E5: FILAMENTOS | O5: MODELADOR | Q5: PRECIFICAÇÃO
A6: Foto | B6: Nome do Produto | C6: Categoria | D6: Cor / Variação | E6: Filamento 1 | F6: g | G6: Filamento 2 | H6: g | I6: Filamento 3 | J6: g | K6: Horas | L6: Bico | M6: Chaveiro? | N6: Ímã? | O6: Modelador | P6: R$ Model | Q6: Custo Est. | R6: Preço Varejo | S6: Preço Atacado | T6: Link Foto (Drive) | U6: Observações | V6: SKU
A7: =IF(T7="","",IMAGE(T7,4,50,50)) | B7: Caixinha Verde e Amarela | C7: Caixinha | D7: Verde e Amarela | E7: Verde | F7: 50 | G7: Amarelo | H7: 30 | J7: 0 | K7: 2.5 | L7: 0.4 | M7: Não | N7: Não | Q7: =IF(F7=0,"",(F7+H7+J7)/1000*'⚙️ Parâmetros'!B6+K7*'⚙️ Parâmetros'!B7*'⚙️ Parâmetros'!B8+K7*'⚙️ Parâmetros'!B9+'⚙️ Parâmetros'!B10+IF(M7="Sim",'⚙️ Parâmetros'!B11,0)+IF(N7="Sim",'⚙️ Parâmetros'!B12,0)+IF(P7="",0,P7)) | R7: =IF(Q7="","",Q7*'⚙️ Parâmetros'!B13) | S7: =IF(Q7="","",Q7*'⚙️ Parâmetros'!B14) | V7: =IF(B7="","",IFERROR(VLOOKUP(C7,'⚙️ Parâmetros'!$A$20:$B$29,2,0)&"-2026-"&TEXT(COUNTIF($B$7:B7,B7),"000"),""))
A8: =IF(T8="","",IMAGE(T8,4,50,50)) | B8: Caixinha Azul e Branca | C8: Caixinha | D8: Azul e Branca | E8: Azul | F8: 50 | G8: Branco | H8: 30 | J8: 0 | K8: 2.5 | L8: 0.4 | M8: Não | N8: Não | Q8: =IF(F8=0,"",(F8+H8+J8)/1000*'⚙️ Parâmetros'!B6+K8*'⚙️ Parâmetros'!B7*'⚙️ Parâmetros'!B8+K8*'⚙️ Parâmetros'!B9+'⚙️ Parâmetros'!B10+IF(M8="Sim",'⚙️ Parâmetros'!B11,0)+IF(N8="Sim",'⚙️ Parâmetros'!B12,0)+IF(P8="",0,P8)) | R8: =IF(Q8="","",Q8*'⚙️ Parâmetros'!B13) | S8: =IF(Q8="","",Q8*'⚙️ Parâmetros'!B14) | V8: =IF(B8="","",IFERROR(VLOOKUP(C8,'⚙️ Parâmetros'!$A$20:$B$29,2,0)&"-2026-"&TEXT(COUNTIF($B$7:B8,B8),"000"),""))
A9: =IF(T9="","",IMAGE(T9,4,50,50)) | B9: Caixinha Branca e Azul | C9: Caixinha | D9: Branca e Azul | E9: Branco | F9: 50 | G9: Azul | H9: 30 | J9: 0 | K9: 2.5 | L9: 0.4 | M9: Não | N9: Não | Q9: =IF(F9=0,"",(F9+H9+J9)/1000*'⚙️ Parâmetros'!B6+K9*'⚙️ Parâmetros'!B7*'⚙️ Parâmetros'!B8+K9*'⚙️ Parâmetros'!B9+'⚙️ Parâmetros'!B10+IF(M9="Sim",'⚙️ Parâmetros'!B11,0)+IF(N9="Sim",'⚙️ Parâmetros'!B12,0)+IF(P9="",0,P9)) | R9: =IF(Q9="","",Q9*'⚙️ Parâmetros'!B13) | S9: =IF(Q9="","",Q9*'⚙️ Parâmetros'!B14) | V9: =IF(B9="","",IFERROR(VLOOKUP(C9,'⚙️ Parâmetros'!$A$20:$B$29,2,0)&"-2026-"&TEXT(COUNTIF($B$7:B9,B9),"000"),""))
A10: =IF(T10="","",IMAGE(T10,4,50,50)) | B10: Chaveiro Flor Rosa | C10: Chaveiro | D10: Rosa e Branco | E10: Rosa | F10: 10 | G10: Branco | H10: 2 | J10: 0 | K10: 1 | L10: 0.4 | M10: Sim | N10: Não | Q10: =IF(F10=0,"",(F10+H10+J10)/1000*'⚙️ Parâmetros'!B6+K10*'⚙️ Parâmetros'!B7*'⚙️ Parâmetros'!B8+K10*'⚙️ Parâmetros'!B9+'⚙️ Parâmetros'!B10+IF(M10="Sim",'⚙️ Parâmetros'!B11,0)+IF(N10="Sim",'⚙️ Parâmetros'!B12,0)+IF(P10="",0,P10)) | R10: =IF(Q10="","",Q10*'⚙️ Parâmetros'!B13) | S10: =IF(Q10="","",Q10*'⚙️ Parâmetros'!B14) | V10: =IF(B10="","",IFERROR(VLOOKUP(C10,'⚙️ Parâmetros'!$A$20:$B$29,2,0)&"-2026-"&TEXT(COUNTIF($B$7:B10,B10),"000"),""))
A11: =IF(T11="","",IMAGE(T11,4,50,50)) | B11: Polvo | C11: Miniatura | D11: Azul | E11: Azul | F11: 30 | G11: Branco | H11: 10 | I11: Preto | J11: 5 | K11: 4 | L11: 0.2 | M11: Não | N11: Não | Q11: =IF(F11=0,"",(F11+H11+J11)/1000*'⚙️ Parâmetros'!B6+K11*'⚙️ Parâmetros'!B7*'⚙️ Parâmetros'!B8+K11*'⚙️ Parâmetros'!B9+'⚙️ Parâmetros'!B10+IF(M11="Sim",'⚙️ Parâmetros'!B11,0)+IF(N11="Sim",'⚙️ Parâmetros'!B12,0)+IF(P11="",0,P11)) | R11: =IF(Q11="","",Q11*'⚙️ Parâmetros'!B13) | S11: =IF(Q11="","",Q11*'⚙️ Parâmetros'!B14) | U11: Estoque: 12 un | V11: =IF(B11="","",IFERROR(VLOOKUP(C11,'⚙️ Parâmetros'!$A$20:$B$29,2,0)&"-2026-"&TEXT(COUNTIF($B$7:B11,B11),"000"),""))
A12: =IF(T12="","",IMAGE(T12,4,50,50)) | B12: Estádio Corinthians | C12: Miniatura | D12: Preto e Branco | E12: Preto | F12: 35 | G12: Branco | H12: 20 | K12: 4.5 | L12: 0.4 | M12: Não | N12: Não | Q12: =IF(F12=0,"",(F12+H12+J12)/1000*'⚙️ Parâmetros'!B6+K12*'⚙️ Parâmetros'!B7*'⚙️ Parâmetros'!B8+K12*'⚙️ Parâmetros'!B9+'⚙️ Parâmetros'!B10+IF(M12="Sim",'⚙️ Parâmetros'!B11,0)+IF(N12="Sim",'⚙️ Parâmetros'!B12,0)+IF(P12="",0,P12)) | R12: =IF(Q12="","",Q12*'⚙️ Parâmetros'!B13) | S12: =IF(Q12="","",Q12*'⚙️ Parâmetros'!B14) | U12: Estádio time Corinthians | V12: =IF(B12="","",IFERROR(VLOOKUP(C12,'⚙️ Parâmetros'!$A$20:$B$29,2,0)&"-2026-"&TEXT(COUNTIF($B$7:B12,B12),"000"),""))
A13: =IF(T13="","",IMAGE(T13,4,50,50)) | B13: Estádio Palmeiras | C13: Miniatura | D13: Verde e Branco | E13: Verde | F13: 40 | G13: Branco | H13: 15 | K13: 4.5 | L13: 0.4 | M13: Não | N13: Não | Q13: =IF(F13=0,"",(F13+H13+J13)/1000*'⚙️ Parâmetros'!B6+K13*'⚙️ Parâmetros'!B7*'⚙️ Parâmetros'!B8+K13*'⚙️ Parâmetros'!B9+'⚙️ Parâmetros'!B10+IF(M13="Sim",'⚙️ Parâmetros'!B11,0)+IF(N13="Sim",'⚙️ Parâmetros'!B12,0)+IF(P13="",0,P13)) | R13: =IF(Q13="","",Q13*'⚙️ Parâmetros'!B13) | S13: =IF(Q13="","",Q13*'⚙️ Parâmetros'!B14) | U13: Estádio time Palmeiras | V13: =IF(B13="","",IFERROR(VLOOKUP(C13,'⚙️ Parâmetros'!$A$20:$B$29,2,0)&"-2026-"&TEXT(COUNTIF($B$7:B13,B13),"000"),""))
A14: =IF(T14="","",IMAGE(T14,4,50,50)) | B14: Estádio São Paulo | C14: Miniatura | D14: Vermelho, Branco e Preto | E14: Vermelho | F14: 25 | G14: Branco | H14: 20 | I14: Preto | J14: 10 | K14: 4.5 | L14: 0.4 | M14: Não | N14: Não | Q14: =IF(F14=0,"",(F14+H14+J14)/1000*'⚙️ Parâmetros'!B6+K14*'⚙️ Parâmetros'!B7*'⚙️ Parâmetros'!B8+K14*'⚙️ Parâmetros'!B9+'⚙️ Parâmetros'!B10+IF(M14="Sim",'⚙️ Parâmetros'!B11,0)+IF(N14="Sim",'⚙️ Parâmetros'!B12,0)+IF(P14="",0,P14)) | R14: =IF(Q14="","",Q14*'⚙️ Parâmetros'!B13) | S14: =IF(Q14="","",Q14*'⚙️ Parâmetros'!B14) | U14: Estádio time São Paulo | V14: =IF(B14="","",IFERROR(VLOOKUP(C14,'⚙️ Parâmetros'!$A$20:$B$29,2,0)&"-2026-"&TEXT(COUNTIF($B$7:B14,B14),"000"),""))
A15: =IF(T15="","",IMAGE(T15,4,50,50)) | B15: Martelo Thor | C15: Miniatura | D15: Cinza e Prata | E15: Cinza | F15: 30 | K15: 3 | L15: 0.4 | M15: Não | N15: Não | Q15: =IF(F15=0,"",(F15+H15+J15)/1000*'⚙️ Parâmetros'!B6+K15*'⚙️ Parâmetros'!B7*'⚙️ Parâmetros'!B8+K15*'⚙️ Parâmetros'!B9+'⚙️ Parâmetros'!B10+IF(M15="Sim",'⚙️ Parâmetros'!B11,0)+IF(N15="Sim",'⚙️ Parâmetros'!B12,0)+IF(P15="",0,P15)) | R15: =IF(Q15="","",Q15*'⚙️ Parâmetros'!B13) | S15: =IF(Q15="","",Q15*'⚙️ Parâmetros'!B14) | U15: Martelo do Thor | V15: =IF(B15="","",IFERROR(VLOOKUP(C15,'⚙️ Parâmetros'!$A$20:$B$29,2,0)&"-2026-"&TEXT(COUNTIF($B$7:B15,B15),"000"),""))
A16: =IF(T16="","",IMAGE(T16,4,50,50)) | B16: Estádio Santos | C16: Miniatura | D16: Branco e Preto | E16: Branco | F16: 35 | G16: Preto | H16: 15 | K16: 4.5 | L16: 0.4 | M16: Não | N16: Não | Q16: =IF(F16=0,"",(F16+H16+J16)/1000*'⚙️ Parâmetros'!B6+K16*'⚙️ Parâmetros'!B7*'⚙️ Parâmetros'!B8+K16*'⚙️ Parâmetros'!B9+'⚙️ Parâmetros'!B10+IF(M16="Sim",'⚙️ Parâmetros'!B11,0)+IF(N16="Sim",'⚙️ Parâmetros'!B12,0)+IF(P16="",0,P16)) | R16: =IF(Q16="","",Q16*'⚙️ Parâmetros'!B13) | S16: =IF(Q16="","",Q16*'⚙️ Parâmetros'!B14) | U16: Estádio time Santos | V16: =IF(B16="","",IFERROR(VLOOKUP(C16,'⚙️ Parâmetros'!$A$20:$B$29,2,0)&"-2026-"&TEXT(COUNTIF($B$7:B16,B16),"000"),""))
A17: =IF(T17="","",IMAGE(T17,4,50,50)) | B17: Estádio Flamengo | C17: Miniatura | D17: Vermelho e Preto | E17: Vermelho | F17: 35 | G17: Preto | H17: 15 | K17: 4.5 | L17: 0.4 | M17: Não | N17: Não | Q17: =IF(F17=0,"",(F17+H17+J17)/1000*'⚙️ Parâmetros'!B6+K17*'⚙️ Parâmetros'!B7*'⚙️ Parâmetros'!B8+K17*'⚙️ Parâmetros'!B9+'⚙️ Parâmetros'!B10+IF(M17="Sim",'⚙️ Parâmetros'!B11,0)+IF(N17="Sim",'⚙️ Parâmetros'!B12,0)+IF(P17="",0,P17)) | R17: =IF(Q17="","",Q17*'⚙️ Parâmetros'!B13) | S17: =IF(Q17="","",Q17*'⚙️ Parâmetros'!B14) | U17: Estádio time Flamengo | V17: =IF(B17="","",IFERROR(VLOOKUP(C17,'⚙️ Parâmetros'!$A$20:$B$29,2,0)&"-2026-"&TEXT(COUNTIF($B$7:B17,B17),"000"),""))
A18: =IF(T18="","",IMAGE(T18,4,50,50)) | B18: Escudo Flamengo | C18: Miniatura | D18: Vermelho e Preto | E18: Vermelho | F18: 10 | G18: Preto | H18: 5 | K18: 1.5 | L18: 0.4 | M18: Não | N18: Não | Q18: =IF(F18=0,"",(F18+H18+J18)/1000*'⚙️ Parâmetros'!B6+K18*'⚙️ Parâmetros'!B7*'⚙️ Parâmetros'!B8+K18*'⚙️ Parâmetros'!B9+'⚙️ Parâmetros'!B10+IF(M18="Sim",'⚙️ Parâmetros'!B11,0)+IF(N18="Sim",'⚙️ Parâmetros'!B12,0)+IF(P18="",0,P18)) | R18: =IF(Q18="","",Q18*'⚙️ Parâmetros'!B13) | S18: =IF(Q18="","",Q18*'⚙️ Parâmetros'!B14) | U18: Escudo time Flamengo | V18: =IF(B18="","",IFERROR(VLOOKUP(C18,'⚙️ Parâmetros'!$A$20:$B$29,2,0)&"-2026-"&TEXT(COUNTIF($B$7:B18,B18),"000"),""))
A19: =IF(T19="","",IMAGE(T19,4,50,50)) | B19: Estela Sensorial Maior | C19: Enfeite/Decoração | D19: Multicolor | E19: Verde | F19: 15 | G19: Amarelo | H19: 10 | I19: Azul | J19: 10 | K19: 3 | L19: 0.4 | M19: Não | N19: Não | Q19: =IF(F19=0,"",(F19+H19+J19)/1000*'⚙️ Parâmetros'!B6+K19*'⚙️ Parâmetros'!B7*'⚙️ Parâmetros'!B8+K19*'⚙️ Parâmetros'!B9+'⚙️ Parâmetros'!B10+IF(M19="Sim",'⚙️ Parâmetros'!B11,0)+IF(N19="Sim",'⚙️ Parâmetros'!B12,0)+IF(P19="",0,P19)) | R19: =IF(Q19="","",Q19*'⚙️ Parâmetros'!B13) | S19: =IF(Q19="","",Q19*'⚙️ Parâmetros'!B14) | U19: Peça sensorial — modelo maior | V19: =IF(B19="","",IFERROR(VLOOKUP(C19,'⚙️ Parâmetros'!$A$20:$B$29,2,0)&"-2026-"&TEXT(COUNTIF($B$7:B19,B19),"000"),""))
A20: =IF(T20="","",IMAGE(T20,4,50,50)) | B20: Minicraft Verde | C20: Miniatura | D20: Verde | E20: Verde | F20: 18 | K20: 2 | L20: 0.4 | M20: Não | N20: Não | Q20: =IF(F20=0,"",(F20+H20+J20)/1000*'⚙️ Parâmetros'!B6+K20*'⚙️ Parâmetros'!B7*'⚙️ Parâmetros'!B8+K20*'⚙️ Parâmetros'!B9+'⚙️ Parâmetros'!B10+IF(M20="Sim",'⚙️ Parâmetros'!B11,0)+IF(N20="Sim",'⚙️ Parâmetros'!B12,0)+IF(P20="",0,P20)) | R20: =IF(Q20="","",Q20*'⚙️ Parâmetros'!B13) | S20: =IF(Q20="","",Q20*'⚙️ Parâmetros'!B14) | U20: Estilo Minecraft | V20: =IF(B20="","",IFERROR(VLOOKUP(C20,'⚙️ Parâmetros'!$A$20:$B$29,2,0)&"-2026-"&TEXT(COUNTIF($B$7:B20,B20),"000"),""))
A21: =IF(T21="","",IMAGE(T21,4,50,50)) | B21: Pentágono Sensorial | C21: Enfeite/Decoração | D21: Multicolor | E21: Vermelho | F21: 12 | G21: Azul | H21: 10 | I21: Amarelo | J21: 8 | K21: 2.5 | L21: 0.4 | M21: Não | N21: Não | Q21: =IF(F21=0,"",(F21+H21+J21)/1000*'⚙️ Parâmetros'!B6+K21*'⚙️ Parâmetros'!B7*'⚙️ Parâmetros'!B8+K21*'⚙️ Parâmetros'!B9+'⚙️ Parâmetros'!B10+IF(M21="Sim",'⚙️ Parâmetros'!B11,0)+IF(N21="Sim",'⚙️ Parâmetros'!B12,0)+IF(P21="",0,P21)) | R21: =IF(Q21="","",Q21*'⚙️ Parâmetros'!B13) | S21: =IF(Q21="","",Q21*'⚙️ Parâmetros'!B14) | U21: Peça sensorial pentágono | V21: =IF(B21="","",IFERROR(VLOOKUP(C21,'⚙️ Parâmetros'!$A$20:$B$29,2,0)&"-2026-"&TEXT(COUNTIF($B$7:B21,B21),"000"),""))
A22: =IF(T22="","",IMAGE(T22,4,50,50)) | B22: Tubarão | C22: Miniatura | D22: Cinza e Azul | E22: Cinza | F22: 20 | G22: Azul | H22: 8 | K22: 2.5 | L22: 0.4 | M22: Não | N22: Não | Q22: =IF(F22=0,"",(F22+H22+J22)/1000*'⚙️ Parâmetros'!B6+K22*'⚙️ Parâmetros'!B7*'⚙️ Parâmetros'!B8+K22*'⚙️ Parâmetros'!B9+'⚙️ Parâmetros'!B10+IF(M22="Sim",'⚙️ Parâmetros'!B11,0)+IF(N22="Sim",'⚙️ Parâmetros'!B12,0)+IF(P22="",0,P22)) | R22: =IF(Q22="","",Q22*'⚙️ Parâmetros'!B13) | S22: =IF(Q22="","",Q22*'⚙️ Parâmetros'!B14) | V22: =IF(B22="","",IFERROR(VLOOKUP(C22,'⚙️ Parâmetros'!$A$20:$B$29,2,0)&"-2026-"&TEXT(COUNTIF($B$7:B22,B22),"000"),""))
A23: =IF(T23="","",IMAGE(T23,4,50,50)) | B23: Nossa Senhora | C23: Miniatura | D23: Branco e Azul | E23: Branco | F23: 20 | G23: Azul | H23: 5 | K23: 3 | L23: 0.4 | M23: Não | N23: Não | Q23: =IF(F23=0,"",(F23+H23+J23)/1000*'⚙️ Parâmetros'!B6+K23*'⚙️ Parâmetros'!B7*'⚙️ Parâmetros'!B8+K23*'⚙️ Parâmetros'!B9+'⚙️ Parâmetros'!B10+IF(M23="Sim",'⚙️ Parâmetros'!B11,0)+IF(N23="Sim",'⚙️ Parâmetros'!B12,0)+IF(P23="",0,P23)) | R23: =IF(Q23="","",Q23*'⚙️ Parâmetros'!B13) | S23: =IF(Q23="","",Q23*'⚙️ Parâmetros'!B14) | U23: Imagem religiosa | V23: =IF(B23="","",IFERROR(VLOOKUP(C23,'⚙️ Parâmetros'!$A$20:$B$29,2,0)&"-2026-"&TEXT(COUNTIF($B$7:B23,B23),"000"),""))
A24: =IF(T24="","",IMAGE(T24,4,50,50)) | B24: Gato Preto | C24: Miniatura | D24: Preto | E24: Preto | F24: 15 | K24: 2 | L24: 0.4 | M24: Não | N24: Não | Q24: =IF(F24=0,"",(F24+H24+J24)/1000*'⚙️ Parâmetros'!B6+K24*'⚙️ Parâmetros'!B7*'⚙️ Parâmetros'!B8+K24*'⚙️ Parâmetros'!B9+'⚙️ Parâmetros'!B10+IF(M24="Sim",'⚙️ Parâmetros'!B11,0)+IF(N24="Sim",'⚙️ Parâmetros'!B12,0)+IF(P24="",0,P24)) | R24: =IF(Q24="","",Q24*'⚙️ Parâmetros'!B13) | S24: =IF(Q24="","",Q24*'⚙️ Parâmetros'!B14) | V24: =IF(B24="","",IFERROR(VLOOKUP(C24,'⚙️ Parâmetros'!$A$20:$B$29,2,0)&"-2026-"&TEXT(COUNTIF($B$7:B24,B24),"000"),""))
A25: =IF(T25="","",IMAGE(T25,4,50,50)) | B25: Stormtrooper | C25: Miniatura | D25: Branco | E25: Branco | F25: 22 | K25: 2.5 | L25: 0.4 | M25: Não | N25: Não | Q25: =IF(F25=0,"",(F25+H25+J25)/1000*'⚙️ Parâmetros'!B6+K25*'⚙️ Parâmetros'!B7*'⚙️ Parâmetros'!B8+K25*'⚙️ Parâmetros'!B9+'⚙️ Parâmetros'!B10+IF(M25="Sim",'⚙️ Parâmetros'!B11,0)+IF(N25="Sim",'⚙️ Parâmetros'!B12,0)+IF(P25="",0,P25)) | R25: =IF(Q25="","",Q25*'⚙️ Parâmetros'!B13) | S25: =IF(Q25="","",Q25*'⚙️ Parâmetros'!B14) | U25: Star Wars | V25: =IF(B25="","",IFERROR(VLOOKUP(C25,'⚙️ Parâmetros'!$A$20:$B$29,2,0)&"-2026-"&TEXT(COUNTIF($B$7:B25,B25),"000"),""))
A26: =IF(T26="","",IMAGE(T26,4,50,50)) | B26: Copo Stanley | C26: Enfeite/Decoração | D26: Variado | E26: Preto | F26: 12 | K26: 1.5 | L26: 0.4 | M26: Não | N26: Não | Q26: =IF(F26=0,"",(F26+H26+J26)/1000*'⚙️ Parâmetros'!B6+K26*'⚙️ Parâmetros'!B7*'⚙️ Parâmetros'!B8+K26*'⚙️ Parâmetros'!B9+'⚙️ Parâmetros'!B10+IF(M26="Sim",'⚙️ Parâmetros'!B11,0)+IF(N26="Sim",'⚙️ Parâmetros'!B12,0)+IF(P26="",0,P26)) | R26: =IF(Q26="","",Q26*'⚙️ Parâmetros'!B13) | S26: =IF(Q26="","",Q26*'⚙️ Parâmetros'!B14) | U26: Base/suporte copo Stanley | V26: =IF(B26="","",IFERROR(VLOOKUP(C26,'⚙️ Parâmetros'!$A$20:$B$29,2,0)&"-2026-"&TEXT(COUNTIF($B$7:B26,B26),"000"),""))
A27: =IF(T27="","",IMAGE(T27,4,50,50)) | B27: Homem de Ferro | C27: Miniatura | D27: Vermelho e Dourado | E27: Vermelho | F27: 18 | G27: Amarelo | H27: 7 | K27: 2.5 | L27: 0.4 | M27: Não | N27: Não | Q27: =IF(F27=0,"",(F27+H27+J27)/1000*'⚙️ Parâmetros'!B6+K27*'⚙️ Parâmetros'!B7*'⚙️ Parâmetros'!B8+K27*'⚙️ Parâmetros'!B9+'⚙️ Parâmetros'!B10+IF(M27="Sim",'⚙️ Parâmetros'!B11,0)+IF(N27="Sim",'⚙️ Parâmetros'!B12,0)+IF(P27="",0,P27)) | R27: =IF(Q27="","",Q27*'⚙️ Parâmetros'!B13) | S27: =IF(Q27="","",Q27*'⚙️ Parâmetros'!B14) | U27: Marvel | V27: =IF(B27="","",IFERROR(VLOOKUP(C27,'⚙️ Parâmetros'!$A$20:$B$29,2,0)&"-2026-"&TEXT(COUNTIF($B$7:B27,B27),"000"),""))
A28: =IF(T28="","",IMAGE(T28,4,50,50)) | B28: Homem Aranha | C28: Miniatura | D28: Vermelho e Azul | E28: Vermelho | F28: 12 | G28: Azul | H28: 10 | K28: 2 | L28: 0.4 | M28: Não | N28: Não | Q28: =IF(F28=0,"",(F28+H28+J28)/1000*'⚙️ Parâmetros'!B6+K28*'⚙️ Parâmetros'!B7*'⚙️ Parâmetros'!B8+K28*'⚙️ Parâmetros'!B9+'⚙️ Parâmetros'!B10+IF(M28="Sim",'⚙️ Parâmetros'!B11,0)+IF(N28="Sim",'⚙️ Parâmetros'!B12,0)+IF(P28="",0,P28)) | R28: =IF(Q28="","",Q28*'⚙️ Parâmetros'!B13) | S28: =IF(Q28="","",Q28*'⚙️ Parâmetros'!B14) | U28: Marvel | V28: =IF(B28="","",IFERROR(VLOOKUP(C28,'⚙️ Parâmetros'!$A$20:$B$29,2,0)&"-2026-"&TEXT(COUNTIF($B$7:B28,B28),"000"),""))
A29: =IF(T29="","",IMAGE(T29,4,50,50)) | B29: Baby Groot | C29: Miniatura | D29: Verde e Marrom | E29: Verde | F29: 15 | G29: Marrom | H29: 5 | K29: 2 | L29: 0.4 | M29: Não | N29: Não | Q29: =IF(F29=0,"",(F29+H29+J29)/1000*'⚙️ Parâmetros'!B6+K29*'⚙️ Parâmetros'!B7*'⚙️ Parâmetros'!B8+K29*'⚙️ Parâmetros'!B9+'⚙️ Parâmetros'!B10+IF(M29="Sim",'⚙️ Parâmetros'!B11,0)+IF(N29="Sim",'⚙️ Parâmetros'!B12,0)+IF(P29="",0,P29)) | R29: =IF(Q29="","",Q29*'⚙️ Parâmetros'!B13) | S29: =IF(Q29="","",Q29*'⚙️ Parâmetros'!B14) | U29: Marvel | V29: =IF(B29="","",IFERROR(VLOOKUP(C29,'⚙️ Parâmetros'!$A$20:$B$29,2,0)&"-2026-"&TEXT(COUNTIF($B$7:B29,B29),"000"),""))
A30: =IF(T30="","",IMAGE(T30,4,50,50)) | B30: Alien | C30: Miniatura | D30: Preto | E30: Preto | F30: 16 | K30: 1.5 | L30: 0.4 | M30: Não | N30: Não | Q30: =IF(F30=0,"",(F30+H30+J30)/1000*'⚙️ Parâmetros'!B6+K30*'⚙️ Parâmetros'!B7*'⚙️ Parâmetros'!B8+K30*'⚙️ Parâmetros'!B9+'⚙️ Parâmetros'!B10+IF(M30="Sim",'⚙️ Parâmetros'!B11,0)+IF(N30="Sim",'⚙️ Parâmetros'!B12,0)+IF(P30="",0,P30)) | R30: =IF(Q30="","",Q30*'⚙️ Parâmetros'!B13) | S30: =IF(Q30="","",Q30*'⚙️ Parâmetros'!B14) | V30: =IF(B30="","",IFERROR(VLOOKUP(C30,'⚙️ Parâmetros'!$A$20:$B$29,2,0)&"-2026-"&TEXT(COUNTIF($B$7:B30,B30),"000"),""))
A31: =IF(T31="","",IMAGE(T31,4,50,50)) | B31: Harry Potter | C31: Miniatura | D31: Variado | E31: Preto | F31: 10 | G31: Vermelho | H31: 8 | I31: Amarelo | J31: 6 | K31: 2.5 | L31: 0.4 | M31: Não | N31: Não | Q31: =IF(F31=0,"",(F31+H31+J31)/1000*'⚙️ Parâmetros'!B6+K31*'⚙️ Parâmetros'!B7*'⚙️ Parâmetros'!B8+K31*'⚙️ Parâmetros'!B9+'⚙️ Parâmetros'!B10+IF(M31="Sim",'⚙️ Parâmetros'!B11,0)+IF(N31="Sim",'⚙️ Parâmetros'!B12,0)+IF(P31="",0,P31)) | R31: =IF(Q31="","",Q31*'⚙️ Parâmetros'!B13) | S31: =IF(Q31="","",Q31*'⚙️ Parâmetros'!B14) | V31: =IF(B31="","",IFERROR(VLOOKUP(C31,'⚙️ Parâmetros'!$A$20:$B$29,2,0)&"-2026-"&TEXT(COUNTIF($B$7:B31,B31),"000"),""))
A32: =IF(T32="","",IMAGE(T32,4,50,50)) | B32: Cone | C32: Enfeite/Decoração | D32: Laranja e Amarelo | E32: Laranja | F32: 12 | G32: Amarelo | H32: 8 | K32: 2 | L32: 0.4 | M32: Não | N32: Não | Q32: =IF(F32=0,"",(F32+H32+J32)/1000*'⚙️ Parâmetros'!B6+K32*'⚙️ Parâmetros'!B7*'⚙️ Parâmetros'!B8+K32*'⚙️ Parâmetros'!B9+'⚙️ Parâmetros'!B10+IF(M32="Sim",'⚙️ Parâmetros'!B11,0)+IF(N32="Sim",'⚙️ Parâmetros'!B12,0)+IF(P32="",0,P32)) | R32: =IF(Q32="","",Q32*'⚙️ Parâmetros'!B13) | S32: =IF(Q32="","",Q32*'⚙️ Parâmetros'!B14) | U32: Peça sensorial cone | V32: =IF(B32="","",IFERROR(VLOOKUP(C32,'⚙️ Parâmetros'!$A$20:$B$29,2,0)&"-2026-"&TEXT(COUNTIF($B$7:B32,B32),"000"),""))
A33: =IF(T33="","",IMAGE(T33,4,50,50)) | B33: Pokebola | C33: Miniatura | D33: Vermelho e Branco | E33: Vermelho | F33: 8 | G33: Branco | H33: 4 | K33: 1 | L33: 0.4 | M33: Não | N33: Não | Q33: =IF(F33=0,"",(F33+H33+J33)/1000*'⚙️ Parâmetros'!B6+K33*'⚙️ Parâmetros'!B7*'⚙️ Parâmetros'!B8+K33*'⚙️ Parâmetros'!B9+'⚙️ Parâmetros'!B10+IF(M33="Sim",'⚙️ Parâmetros'!B11,0)+IF(N33="Sim",'⚙️ Parâmetros'!B12,0)+IF(P33="",0,P33)) | R33: =IF(Q33="","",Q33*'⚙️ Parâmetros'!B13) | S33: =IF(Q33="","",Q33*'⚙️ Parâmetros'!B14) | U33: Pokémon | V33: =IF(B33="","",IFERROR(VLOOKUP(C33,'⚙️ Parâmetros'!$A$20:$B$29,2,0)&"-2026-"&TEXT(COUNTIF($B$7:B33,B33),"000"),""))
A34: =IF(T34="","",IMAGE(T34,4,50,50)) | B34: Fantasma Vermelho | C34: Miniatura | D34: Vermelho | E34: Vermelho | F34: 10 | K34: 1 | L34: 0.4 | M34: Não | N34: Não | Q34: =IF(F34=0,"",(F34+H34+J34)/1000*'⚙️ Parâmetros'!B6+K34*'⚙️ Parâmetros'!B7*'⚙️ Parâmetros'!B8+K34*'⚙️ Parâmetros'!B9+'⚙️ Parâmetros'!B10+IF(M34="Sim",'⚙️ Parâmetros'!B11,0)+IF(N34="Sim",'⚙️ Parâmetros'!B12,0)+IF(P34="",0,P34)) | R34: =IF(Q34="","",Q34*'⚙️ Parâmetros'!B13) | S34: =IF(Q34="","",Q34*'⚙️ Parâmetros'!B14) | U34: Pac-Man | V34: =IF(B34="","",IFERROR(VLOOKUP(C34,'⚙️ Parâmetros'!$A$20:$B$29,2,0)&"-2026-"&TEXT(COUNTIF($B$7:B34,B34),"000"),""))
A35: =IF(T35="","",IMAGE(T35,4,50,50)) | B35: Dado RPG | C35: Enfeite/Decoração | D35: Variado | E35: Branco | F35: 8 | G35: Preto | H35: 2 | K35: 1 | L35: 0.4 | M35: Não | N35: Não | Q35: =IF(F35=0,"",(F35+H35+J35)/1000*'⚙️ Parâmetros'!B6+K35*'⚙️ Parâmetros'!B7*'⚙️ Parâmetros'!B8+K35*'⚙️ Parâmetros'!B9+'⚙️ Parâmetros'!B10+IF(M35="Sim",'⚙️ Parâmetros'!B11,0)+IF(N35="Sim",'⚙️ Parâmetros'!B12,0)+IF(P35="",0,P35)) | R35: =IF(Q35="","",Q35*'⚙️ Parâmetros'!B13) | S35: =IF(Q35="","",Q35*'⚙️ Parâmetros'!B14) | U35: Dado 3D RPG | V35: =IF(B35="","",IFERROR(VLOOKUP(C35,'⚙️ Parâmetros'!$A$20:$B$29,2,0)&"-2026-"&TEXT(COUNTIF($B$7:B35,B35),"000"),""))
A36: =IF(T36="","",IMAGE(T36,4,50,50)) | B36: Mala | C36: Miniatura | D36: Marrom | E36: Marrom | F36: 14 | K36: 1.5 | L36: 0.4 | M36: Não | N36: Não | Q36: =IF(F36=0,"",(F36+H36+J36)/1000*'⚙️ Parâmetros'!B6+K36*'⚙️ Parâmetros'!B7*'⚙️ Parâmetros'!B8+K36*'⚙️ Parâmetros'!B9+'⚙️ Parâmetros'!B10+IF(M36="Sim",'⚙️ Parâmetros'!B11,0)+IF(N36="Sim",'⚙️ Parâmetros'!B12,0)+IF(P36="",0,P36)) | R36: =IF(Q36="","",Q36*'⚙️ Parâmetros'!B13) | S36: =IF(Q36="","",Q36*'⚙️ Parâmetros'!B14) | V36: =IF(B36="","",IFERROR(VLOOKUP(C36,'⚙️ Parâmetros'!$A$20:$B$29,2,0)&"-2026-"&TEXT(COUNTIF($B$7:B36,B36),"000"),""))
A37: =IF(T37="","",IMAGE(T37,4,50,50)) | B37: Jacaré | C37: Miniatura | D37: Verde | E37: Verde | F37: 18 | K37: 2 | L37: 0.4 | M37: Não | N37: Não | Q37: =IF(F37=0,"",(F37+H37+J37)/1000*'⚙️ Parâmetros'!B6+K37*'⚙️ Parâmetros'!B7*'⚙️ Parâmetros'!B8+K37*'⚙️ Parâmetros'!B9+'⚙️ Parâmetros'!B10+IF(M37="Sim",'⚙️ Parâmetros'!B11,0)+IF(N37="Sim",'⚙️ Parâmetros'!B12,0)+IF(P37="",0,P37)) | R37: =IF(Q37="","",Q37*'⚙️ Parâmetros'!B13) | S37: =IF(Q37="","",Q37*'⚙️ Parâmetros'!B14) | V37: =IF(B37="","",IFERROR(VLOOKUP(C37,'⚙️ Parâmetros'!$A$20:$B$29,2,0)&"-2026-"&TEXT(COUNTIF($B$7:B37,B37),"000"),""))
A38: =IF(T38="","",IMAGE(T38,4,50,50)) | B38: Bloco de Interrogação Mario | C38: Miniatura | D38: Amarelo | E38: Amarelo | F38: 15 | K38: 1.5 | L38: 0.4 | M38: Não | N38: Não | Q38: =IF(F38=0,"",(F38+H38+J38)/1000*'⚙️ Parâmetros'!B6+K38*'⚙️ Parâmetros'!B7*'⚙️ Parâmetros'!B8+K38*'⚙️ Parâmetros'!B9+'⚙️ Parâmetros'!B10+IF(M38="Sim",'⚙️ Parâmetros'!B11,0)+IF(N38="Sim",'⚙️ Parâmetros'!B12,0)+IF(P38="",0,P38)) | R38: =IF(Q38="","",Q38*'⚙️ Parâmetros'!B13) | S38: =IF(Q38="","",Q38*'⚙️ Parâmetros'!B14) | U38: Super Mario | V38: =IF(B38="","",IFERROR(VLOOKUP(C38,'⚙️ Parâmetros'!$A$20:$B$29,2,0)&"-2026-"&TEXT(COUNTIF($B$7:B38,B38),"000"),""))
A39: =IF(T39="","",IMAGE(T39,4,50,50)) | B39: Boca Abridor de Garrafa | C39: Plaquinha | D39: Variado | E39: Preto | F39: 30 | G39: Branco | H39: 5 | K39: 3 | L39: 0.4 | M39: Não | N39: Não | Q39: =IF(F39=0,"",(F39+H39+J39)/1000*'⚙️ Parâmetros'!B6+K39*'⚙️ Parâmetros'!B7*'⚙️ Parâmetros'!B8+K39*'⚙️ Parâmetros'!B9+'⚙️ Parâmetros'!B10+IF(M39="Sim",'⚙️ Parâmetros'!B11,0)+IF(N39="Sim",'⚙️ Parâmetros'!B12,0)+IF(P39="",0,P39)) | R39: =IF(Q39="","",Q39*'⚙️ Parâmetros'!B13) | S39: =IF(Q39="","",Q39*'⚙️ Parâmetros'!B14) | U39: Abridor de garrafa — boca | V39: =IF(B39="","",IFERROR(VLOOKUP(C39,'⚙️ Parâmetros'!$A$20:$B$29,2,0)&"-2026-"&TEXT(COUNTIF($B$7:B39,B39),"000"),""))
A40: =IF(T40="","",IMAGE(T40,4,50,50)) | Q40: =IF(F40=0,"",(F40+H40+J40)/1000*'⚙️ Parâmetros'!B6+K40*'⚙️ Parâmetros'!B7*'⚙️ Parâmetros'!B8+K40*'⚙️ Parâmetros'!B9+'⚙️ Parâmetros'!B10+IF(M40="Sim",'⚙️ Parâmetros'!B11,0)+IF(N40="Sim",'⚙️ Parâmetros'!B12,0)+IF(P40="",0,P40)) | R40: =IF(Q40="","",Q40*'⚙️ Parâmetros'!B13) | S40: =IF(Q40="","",Q40*'⚙️ Parâmetros'!B14) | V40: =IF(B40="","",IFERROR(VLOOKUP(C40,'⚙️ Parâmetros'!$A$20:$B$29,2,0)&"-2026-"&TEXT(COUNTIF($B$7:B40,B40),"000"),""))
A41: =IF(T41="","",IMAGE(T41,4,50,50)) | Q41: =IF(F41=0,"",(F41+H41+J41)/1000*'⚙️ Parâmetros'!B6+K41*'⚙️ Parâmetros'!B7*'⚙️ Parâmetros'!B8+K41*'⚙️ Parâmetros'!B9+'⚙️ Parâmetros'!B10+IF(M41="Sim",'⚙️ Parâmetros'!B11,0)+IF(N41="Sim",'⚙️ Parâmetros'!B12,0)+IF(P41="",0,P41)) | R41: =IF(Q41="","",Q41*'⚙️ Parâmetros'!B13) | S41: =IF(Q41="","",Q41*'⚙️ Parâmetros'!B14) | V41: =IF(B41="","",IFERROR(VLOOKUP(C41,'⚙️ Parâmetros'!$A$20:$B$29,2,0)&"-2026-"&TEXT(COUNTIF($B$7:B41,B41),"000"),""))

Sheet 🎨 Filamento
B1: Taldo Studio 3D · Impressão 3D Personalizada · @TaldoStudio3d · Av. Sebastião Henriques, 575
A3: 💡 Registre Entradas (compras) e Saídas (uso nas impressões)
A4: Filamento / Cor | B4: Tipo | C4: Estoque Inicial (g) | D4: Entradas (g) | E4: Saídas (g) | F4: Saldo (g) | G4: Saldo (kg) | H4: Status
A5: Creality | Hyper PLA | Branco | B5: Hyper PLA | C5: 0 | D5: 0 | E5: 0 | F5: =C5+D5-E5 | G5: =F5/1000 | H5: =IF(F5<200,"⚠️ BAIXO",IF(F5<500,"📦 OK","✅ CHEIO"))
A6: Creality | Hyper PLA | Preto | B6: Hyper PLA | C6: 0 | D6: 0 | E6: 0 | F6: =C6+D6-E6 | G6: =F6/1000 | H6: =IF(F6<200,"⚠️ BAIXO",IF(F6<500,"📦 OK","✅ CHEIO"))
A7: Creality | Hyper PLA | Vermelho | B7: Hyper PLA | C7: 0 | D7: 0 | E7: 0 | F7: =C7+D7-E7 | G7: =F7/1000 | H7: =IF(F7<200,"⚠️ BAIXO",IF(F7<500,"📦 OK","✅ CHEIO"))
A8: Creality | Hyper PLA | Azul | B8: Hyper PLA | C8: 0 | D8: 0 | E8: 0 | F8: =C8+D8-E8 | G8: =F8/1000 | H8: =IF(F8<200,"⚠️ BAIXO",IF(F8<500,"📦 OK","✅ CHEIO"))
A9: Creality | Hyper PLA | Cinza | B9: Hyper PLA | C9: 0 | D9: 0 | E9: 0 | F9: =C9+D9-E9 | G9: =F9/1000 | H9: =IF(F9<200,"⚠️ BAIXO",IF(F9<500,"📦 OK","✅ CHEIO"))
A10: Creality | Hyper PLA | Verde | B10: Hyper PLA | C10: 0 | D10: 0 | E10: 0 | F10: =C10+D10-E10 | G10: =F10/1000 | H10: =IF(F10<200,"⚠️ BAIXO",IF(F10<500,"📦 OK","✅ CHEIO"))
A11: Creality | Hyper PLA | Amarelo | B11: Hyper PLA | C11: 0 | D11: 0 | E11: 0 | F11: =C11+D11-E11 | G11: =F11/1000 | H11: =IF(F11<200,"⚠️ BAIXO",IF(F11<500,"📦 OK","✅ CHEIO"))
A12: Creality | Hyper PLA | Laranja | B12: Hyper PLA | C12: 0 | D12: 0 | E12: 0 | F12: =C12+D12-E12 | G12: =F12/1000 | H12: =IF(F12<200,"⚠️ BAIXO",IF(F12<500,"📦 OK","✅ CHEIO"))
A13: Creality | Hyper PLA | Rosa | B13: Hyper PLA | C13: 0 | D13: 0 | E13: 0 | F13: =C13+D13-E13 | G13: =F13/1000 | H13: =IF(F13<200,"⚠️ BAIXO",IF(F13<500,"📦 OK","✅ CHEIO"))
A14: Creality | Hyper PLA | Roxo | B14: Hyper PLA | C14: 0 | D14: 0 | E14: 0 | F14: =C14+D14-E14 | G14: =F14/1000 | H14: =IF(F14<200,"⚠️ BAIXO",IF(F14<500,"📦 OK","✅ CHEIO"))
A15: Creality | Hyper PLA RFID | Vermelho | B15: Hyper PLA RFID | C15: 0 | D15: 0 | E15: 0 | F15: =C15+D15-E15 | G15: =F15/1000 | H15: =IF(F15<200,"⚠️ BAIXO",IF(F15<500,"📦 OK","✅ CHEIO"))
A16: Creality | Hyper PLA RFID | Azul | B16: Hyper PLA RFID | C16: 0 | D16: 0 | E16: 0 | F16: =C16+D16-E16 | G16: =F16/1000 | H16: =IF(F16<200,"⚠️ BAIXO",IF(F16<500,"📦 OK","✅ CHEIO"))
... A387: Soleyin | PLA Matte | Verde | B387: PLA Matte | C387: 0 | D387: 0 | E387: 0 | F387: =C387+D387-E387 | G387: =F387/1000 | H387: =IF(F387<200,"⚠️ BAIXO",IF(F387<500,"📦 OK","✅ CHEIO"))

Sheet 🧾 Romaneio
B1: Taldo Studio 3D · Impressão 3D Personalizada · @TaldoStudio3d · Av. Sebastião Henriques, 575
A4: Nº | B4: Data | C4: Cliente | D4: WhatsApp | E4: Tipo Pedido | F4: Máquina | G4: Prazo | H4: Observações
E5: Pedido | F5: M1
A7: 💡 Selecione o produto → preços automáticos → copie para 📦 Pedidos quando confirmar
E8: PRECIFICAÇÃO
A9: # | B9: Produto | C9: Qtd | D9: Varejo / Atacado | E9: Custo Est. | F9: Sugerido | G9: Valor Final | H9: Total
A10: 1 | D10: Varejo | E10: =IF(B10="","",IFERROR(VLOOKUP(B10,'📋 Catálogo'!$B$7:$S$41,16,0),"")) | F10: =IF(B10="","",IF(D10="Atacado",IFERROR(VLOOKUP(B10,'📋 Catálogo'!$B$7:$S$41,18,0),""),IFERROR(VLOOKUP(B10,'📋 Catálogo'!$B$7:$S$41,17,0),""))) | G10: =IF(F10="","",F10) | H10: =IF(OR(C10="",G10=""),"",C10*G10)
A11: 2 | D11: Varejo | E11: =IF(B11="","",IFERROR(VLOOKUP(B11,'📋 Catálogo'!$B$7:$S$41,16,0),"")) | F11: =IF(B11="","",IF(D11="Atacado",IFERROR(VLOOKUP(B11,'📋 Catálogo'!$B$7:$S$41,18,0),""),IFERROR(VLOOKUP(B11,'📋 Catálogo'!$B$7:$S$41,17,0),""))) | G11: =IF(F11="","",F11) | H11: =IF(OR(C11="",G11=""),"",C11*G11)
A12: 3 | D12: Varejo | E12: =IF(B12="","",IFERROR(VLOOKUP(B12,'📋 Catálogo'!$B$7:$S$41,16,0),"")) | F12: =IF(B12="","",IF(D12="Atacado",IFERROR(VLOOKUP(B12,'📋 Catálogo'!$B$7:$S$41,18,0),""),IFERROR(VLOOKUP(B12,'📋 Catálogo'!$B$7:$S$41,17,0),""))) | G12: =IF(F12="","",F12) | H12: =IF(OR(C12="",G12=""),"",C12*G12)
A13: 4 | D13: Varejo | E13: =IF(B13="","",IFERROR(VLOOKUP(B13,'📋 Catálogo'!$B$7:$S$41,16,0),"")) | F13: =IF(B13="","",IF(D13="Atacado",IFERROR(VLOOKUP(B13,'📋 Catálogo'!$B$7:$S$41,18,0),""),IFERROR(VLOOKUP(B13,'📋 Catálogo'!$B$7:$S$41,17,0),""))) | G13: =IF(F13="","",F13) | H13: =IF(OR(C13="",G13=""),"",C13*G13)
A14: 5 | D14: Varejo | E14: =IF(B14="","",IFERROR(VLOOKUP(B14,'📋 Catálogo'!$B$7:$S$41,16,0),"")) | F14: =IF(B14="","",IF(D14="Atacado",IFERROR(VLOOKUP(B14,'📋 Catálogo'!$B$7:$S$41,18,0),""),IFERROR(VLOOKUP(B14,'📋 Catálogo'!$B$7:$S$41,17,0),""))) | G14: =IF(F14="","",F14) | H14: =IF(OR(C14="",G14=""),"",C14*G14)
A15: 6 | D15: Varejo | E15: =IF(B15="","",IFERROR(VLOOKUP(B15,'📋 Catálogo'!$B$7:$S$41,16,0),"")) | F15: =IF(B15="","",IF(D15="Atacado",IFERROR(VLOOKUP(B15,'📋 Catálogo'!$B$7:$S$41,18,0),""),IFERROR(VLOOKUP(B15,'📋 Catálogo'!$B$7:$S$41,17,0),""))) | G15: =IF(F15="","",F15) | H15: =IF(OR(C15="",G15=""),"",C15*G15)
A16: 7 | D16: Varejo | E16: =IF(B16="","",IFERROR(VLOOKUP(B16,'📋 Catálogo'!$B$7:$S$41,16,0),"")) | F16: =IF(B16="","",IF(D16="Atacado",IFERROR(VLOOKUP(B16,'📋 Catálogo'!$B$7:$S$41,18,0),""),IFERROR(VLOOKUP(B16,'📋 Catálogo'!$B$7:$S$41,17,0),""))) | G16: =IF(F16="","",F16) | H16: =IF(OR(C16="",G16=""),"",C16*G16)
A17: 8 | D17: Varejo | E17: =IF(B17="","",IFERROR(VLOOKUP(B17,'📋 Catálogo'!$B$7:$S$41,16,0),"")) | F17: =IF(B17="","",IF(D17="Atacado",IFERROR(VLOOKUP(B17,'📋 Catálogo'!$B$7:$S$41,18,0),""),IFERROR(VLOOKUP(B17,'📋 Catálogo'!$B$7:$S$41,17,0),""))) | G17: =IF(F17="","",F17) | H17: =IF(OR(C17="",G17=""),"",C17*G17)
A18: 9 | D18: Varejo | E18: =IF(B18="","",IFERROR(VLOOKUP(B18,'📋 Catálogo'!$B$7:$S$41,16,0),"")) | F18: =IF(B18="","",IF(D18="Atacado",IFERROR(VLOOKUP(B18,'📋 Catálogo'!$B$7:$S$41,18,0),""),IFERROR(VLOOKUP(B18,'📋 Catálogo'!$B$7:$S$41,17,0),""))) | G18: =IF(F18="","",F18) | H18: =IF(OR(C18="",G18=""),"",C18*G18)
A19: 10 | D19: Varejo | E19: =IF(B19="","",IFERROR(VLOOKUP(B19,'📋 Catálogo'!$B$7:$S$41,16,0),"")) | F19: =IF(B19="","",IF(D19="Atacado",IFERROR(VLOOKUP(B19,'📋 Catálogo'!$B$7:$S$41,18,0),""),IFERROR(VLOOKUP(B19,'📋 Catálogo'!$B$7:$S$41,17,0),""))) | G19: =IF(F19="","",F19) | H19: =IF(OR(C19="",G19=""),"",C19*G19)
A20: 11 | D20: Varejo | E20: =IF(B20="","",IFERROR(VLOOKUP(B20,'📋 Catálogo'!$B$7:$S$41,16,0),"")) | F20: =IF(B20="","",IF(D20="Atacado",IFERROR(VLOOKUP(B20,'📋 Catálogo'!$B$7:$S$41,18,0),""),IFERROR(VLOOKUP(B20,'📋 Catálogo'!$B$7:$S$41,17,0),""))) | G20: =IF(F20="","",F20) | H20: =IF(OR(C20="",G20=""),"",C20*G20)
A21: 12 | D21: Varejo | E21: =IF(B21="","",IFERROR(VLOOKUP(B21,'📋 Catálogo'!$B$7:$S$41,16,0),"")) | F21: =IF(B21="","",IF(D21="Atacado",IFERROR(VLOOKUP(B21,'📋 Catálogo'!$B$7:$S$41,18,0),""),IFERROR(VLOOKUP(B21,'📋 Catálogo'!$B$7:$S$41,17,0),""))) | G21: =IF(F21="","",F21) | H21: =IF(OR(C21="",G21=""),"",C21*G21)
... A24: 15 | D24: Varejo | E24: =IF(B24="","",IFERROR(VLOOKUP(B24,'📋 Catálogo'!$B$7:$S$41,16,0),"")) | F24: =IF(B24="","",IF(D24="Atacado",IFERROR(VLOOKUP(B24,'📋 Catálogo'!$B$7:$S$41,18,0),""),IFERROR(VLOOKUP(B24,'📋 Catálogo'!$B$7:$S$41,17,0),""))) | G24: =IF(F24="","",F24) | H24: =IF(OR(C24="",G24=""),"",C24*G24)
A26: TOTAL PEÇAS: | C26: =SUM(C10:C24) | E26: CUSTO TOTAL: | F26: =SUMPRODUCT(C10:C24,E10:E24) | G26: TOTAL R$: | H26: =SUM(H10:H24)
A28: ✅ Após preencher: 🖨️ TALDO → Confirmar Pedido

Sheet 📦 Pedidos
B1: Taldo Studio 3D · Impressão 3D Personalizada · @TaldoStudio3d · Av. Sebastião Henriques, 575
A4: SKU | B4: Data | C4: Cliente | D4: WhatsApp | E4: Produto | F4: Qtd | G4: Valor Unit. | H4: Total | I4: Tipo V/A | J4: Status | K4: Máquina
A5: =IF(E5="","",IFERROR(VLOOKUP(E5,'📋 Catálogo'!$B$7:$V$41,21,0),"")) | H5: =IF(OR(F5="",G5=""),"",F5*G5)
A6: =IF(E6="","",IFERROR(VLOOKUP(E6,'📋 Catálogo'!$B$7:$V$41,21,0),"")) | H6: =IF(OR(F6="",G6=""),"",F6*G6)
A7: =IF(E7="","",IFERROR(VLOOKUP(E7,'📋 Catálogo'!$B$7:$V$41,21,0),"")) | H7: =IF(OR(F7="",G7=""),"",F7*G7)
A8: =IF(E8="","",IFERROR(VLOOKUP(E8,'📋 Catálogo'!$B$7:$V$41,21,0),"")) | H8: =IF(OR(F8="",G8=""),"",F8*G8)
A9: =IF(E9="","",IFERROR(VLOOKUP(E9,'📋 Catálogo'!$B$7:$V$41,21,0),"")) | H9: =IF(OR(F9="",G9=""),"",F9*G9)
A10: =IF(E10="","",IFERROR(VLOOKUP(E10,'📋 Catálogo'!$B$7:$V$41,21,0),"")) | H10: =IF(OR(F10="",G10=""),"",F10*G10)
A11: =IF(E11="","",IFERROR(VLOOKUP(E11,'📋 Catálogo'!$B$7:$V$41,21,0),"")) | H11: =IF(OR(F11="",G11=""),"",F11*G11)
A12: =IF(E12="","",IFERROR(VLOOKUP(E12,'📋 Catálogo'!$B$7:$V$41,21,0),"")) | H12: =IF(OR(F12="",G12=""),"",F12*G12)
A13: =IF(E13="","",IFERROR(VLOOKUP(E13,'📋 Catálogo'!$B$7:$V$41,21,0),"")) | H13: =IF(OR(F13="",G13=""),"",F13*G13)
A14: =IF(E14="","",IFERROR(VLOOKUP(E14,'📋 Catálogo'!$B$7:$V$41,21,0),"")) | H14: =IF(OR(F14="",G14=""),"",F14*G14)
A15: =IF(E15="","",IFERROR(VLOOKUP(E15,'📋 Catálogo'!$B$7:$V$41,21,0),"")) | H15: =IF(OR(F15="",G15=""),"",F15*G15)
A16: =IF(E16="","",IFERROR(VLOOKUP(E16,'📋 Catálogo'!$B$7:$V$41,21,0),"")) | H16: =IF(OR(F16="",G16=""),"",F16*G16)
... A204: =IF(E204="","",IFERROR(VLOOKUP(E204,'📋 Catálogo'!$B$7:$V$41,21,0),"")) | H204: =IF(OR(F204="",G204=""),"",F204*G204)

Sheet 🖨️ Produção
B1: Taldo Studio 3D · Impressão 3D Personalizada · @TaldoStudio3d · Av. Sebastião Henriques, 575
A4: 🖨️ APENAS o que precisa ser FABRICADO (Pedido − Estoque disponível)
A5: SKU | B5: Data | C5: Cliente | D5: Produto | E5: Qtd Pedida | F5: Qtd Estoque | G5: A FABRICAR | H5: Máquina | I5: Bico | J5: Horas | K5: Status
G6: =IF(D6="","",MAX(0,E6-F6)) | I6: =IF(D6="","",IFERROR(VLOOKUP(D6,'📋 Catálogo'!$B$7:$L$41,11,0),"")) | J6: =IF(D6="","",IFERROR(VLOOKUP(D6,'📋 Catálogo'!$B$7:$L$41,10,0),""))
G7: =IF(D7="","",MAX(0,E7-F7)) | I7: =IF(D7="","",IFERROR(VLOOKUP(D7,'📋 Catálogo'!$B$7:$L$41,11,0),"")) | J7: =IF(D7="","",IFERROR(VLOOKUP(D7,'📋 Catálogo'!$B$7:$L$41,10,0),""))
G8: =IF(D8="","",MAX(0,E8-F8)) | I8: =IF(D8="","",IFERROR(VLOOKUP(D8,'📋 Catálogo'!$B$7:$L$41,11,0),"")) | J8: =IF(D8="","",IFERROR(VLOOKUP(D8,'📋 Catálogo'!$B$7:$L$41,10,0),""))
G9: =IF(D9="","",MAX(0,E9-F9)) | I9: =IF(D9="","",IFERROR(VLOOKUP(D9,'📋 Catálogo'!$B$7:$L$41,11,0),"")) | J9: =IF(D9="","",IFERROR(VLOOKUP(D9,'📋 Catálogo'!$B$7:$L$41,10,0),""))
G10: =IF(D10="","",MAX(0,E10-F10)) | I10: =IF(D10="","",IFERROR(VLOOKUP(D10,'📋 Catálogo'!$B$7:$L$41,11,0),"")) | J10: =IF(D10="","",IFERROR(VLOOKUP(D10,'📋 Catálogo'!$B$7:$L$41,10,0),""))
G11: =IF(D11="","",MAX(0,E11-F11)) | I11: =IF(D11="","",IFERROR(VLOOKUP(D11,'📋 Catálogo'!$B$7:$L$41,11,0),"")) | J11: =IF(D11="","",IFERROR(VLOOKUP(D11,'📋 Catálogo'!$B$7:$L$41,10,0),""))
G12: =IF(D12="","",MAX(0,E12-F12)) | I12: =IF(D12="","",IFERROR(VLOOKUP(D12,'📋 Catálogo'!$B$7:$L$41,11,0),"")) | J12: =IF(D12="","",IFERROR(VLOOKUP(D12,'📋 Catálogo'!$B$7:$L$41,10,0),""))
G13: =IF(D13="","",MAX(0,E13-F13)) | I13: =IF(D13="","",IFERROR(VLOOKUP(D13,'📋 Catálogo'!$B$7:$L$41,11,0),"")) | J13: =IF(D13="","",IFERROR(VLOOKUP(D13,'📋 Catálogo'!$B$7:$L$41,10,0),""))
G14: =IF(D14="","",MAX(0,E14-F14)) | I14: =IF(D14="","",IFERROR(VLOOKUP(D14,'📋 Catálogo'!$B$7:$L$41,11,0),"")) | J14: =IF(D14="","",IFERROR(VLOOKUP(D14,'📋 Catálogo'!$B$7:$L$41,10,0),""))
G15: =IF(D15="","",MAX(0,E15-F15)) | I15: =IF(D15="","",IFERROR(VLOOKUP(D15,'📋 Catálogo'!$B$7:$L$41,11,0),"")) | J15: =IF(D15="","",IFERROR(VLOOKUP(D15,'📋 Catálogo'!$B$7:$L$41,10,0),""))
G16: =IF(D16="","",MAX(0,E16-F16)) | I16: =IF(D16="","",IFERROR(VLOOKUP(D16,'📋 Catálogo'!$B$7:$L$41,11,0),"")) | J16: =IF(D16="","",IFERROR(VLOOKUP(D16,'📋 Catálogo'!$B$7:$L$41,10,0),""))
G17: =IF(D17="","",MAX(0,E17-F17)) | I17: =IF(D17="","",IFERROR(VLOOKUP(D17,'📋 Catálogo'!$B$7:$L$41,11,0),"")) | J17: =IF(D17="","",IFERROR(VLOOKUP(D17,'📋 Catálogo'!$B$7:$L$41,10,0),""))
... G205: =IF(D205="","",MAX(0,E205-F205)) | I205: =IF(D205="","",IFERROR(VLOOKUP(D205,'📋 Catálogo'!$B$7:$L$41,11,0),"")) | J205: =IF(D205="","",IFERROR(VLOOKUP(D205,'📋 Catálogo'!$B$7:$L$41,10,0),""))

Sheet 📦 Est. Peças
B1: Taldo Studio 3D · Impressão 3D Personalizada · @TaldoStudio3d · Av. Sebastião Henriques, 575
A4: SKU | B4: Produto | C4: Categoria | D4: Fabricadas | E4: Saídas | F4: Reservadas | G4: Disponível | H4: Status
A5: =IF(B5="","",IFERROR(VLOOKUP(B5,'📋 Catálogo'!$B$7:$V$41,21,0),"")) | B5: Estádio Corinthians | C5: Miniatura | D5: 29 | E5: 0 | F5: 0 | G5: =IF(A5="","",D5-E5-F5) | H5: =IF(A5="","",IF(G5<0,"⚠️ NEGATIVO",IF(G5=0,"⛔ ZERADO",IF(G5<5,"📦 BAIXO","✅ OK"))))
A6: =IF(B6="","",IFERROR(VLOOKUP(B6,'📋 Catálogo'!$B$7:$V$41,21,0),"")) | B6: Estádio Palmeiras | C6: Miniatura | D6: 14 | E6: 0 | F6: 0 | G6: =IF(A6="","",D6-E6-F6) | H6: =IF(A6="","",IF(G6<0,"⚠️ NEGATIVO",IF(G6=0,"⛔ ZERADO",IF(G6<5,"📦 BAIXO","✅ OK"))))
A7: =IF(B7="","",IFERROR(VLOOKUP(B7,'📋 Catálogo'!$B$7:$V$41,21,0),"")) | B7: Estádio São Paulo | C7: Miniatura | D7: 15 | E7: 0 | F7: 0 | G7: =IF(A7="","",D7-E7-F7) | H7: =IF(A7="","",IF(G7<0,"⚠️ NEGATIVO",IF(G7=0,"⛔ ZERADO",IF(G7<5,"📦 BAIXO","✅ OK"))))
A8: =IF(B8="","",IFERROR(VLOOKUP(B8,'📋 Catálogo'!$B$7:$V$41,21,0),"")) | B8: Martelo Thor | C8: Miniatura | D8: 31 | E8: 0 | F8: 0 | G8: =IF(A8="","",D8-E8-F8) | H8: =IF(A8="","",IF(G8<0,"⚠️ NEGATIVO",IF(G8=0,"⛔ ZERADO",IF(G8<5,"📦 BAIXO","✅ OK"))))
A9: =IF(B9="","",IFERROR(VLOOKUP(B9,'📋 Catálogo'!$B$7:$V$41,21,0),"")) | B9: Estádio Santos | C9: Miniatura | D9: 15 | E9: 0 | F9: 0 | G9: =IF(A9="","",D9-E9-F9) | H9: =IF(A9="","",IF(G9<0,"⚠️ NEGATIVO",IF(G9=0,"⛔ ZERADO",IF(G9<5,"📦 BAIXO","✅ OK"))))
A10: =IF(B10="","",IFERROR(VLOOKUP(B10,'📋 Catálogo'!$B$7:$V$41,21,0),"")) | B10: Estádio Flamengo | C10: Miniatura | D10: 14 | E10: 0 | F10: 0 | G10: =IF(A10="","",D10-E10-F10) | H10: =IF(A10="","",IF(G10<0,"⚠️ NEGATIVO",IF(G10=0,"⛔ ZERADO",IF(G10<5,"📦 BAIXO","✅ OK"))))
A11: =IF(B11="","",IFERROR(VLOOKUP(B11,'📋 Catálogo'!$B$7:$V$41,21,0),"")) | B11: Escudo Flamengo | C11: Miniatura | D11: 1 | E11: 0 | F11: 0 | G11: =IF(A11="","",D11-E11-F11) | H11: =IF(A11="","",IF(G11<0,"⚠️ NEGATIVO",IF(G11=0,"⛔ ZERADO",IF(G11<5,"📦 BAIXO","✅ OK"))))
A12: =IF(B12="","",IFERROR(VLOOKUP(B12,'📋 Catálogo'!$B$7:$V$41,21,0),"")) | B12: Estela Sensorial Maior | C12: Enfeite/Decoração | D12: 9 | E12: 0 | F12: 0 | G12: =IF(A12="","",D12-E12-F12) | H12: =IF(A12="","",IF(G12<0,"⚠️ NEGATIVO",IF(G12=0,"⛔ ZERADO",IF(G12<5,"📦 BAIXO","✅ OK"))))
A13: =IF(B13="","",IFERROR(VLOOKUP(B13,'📋 Catálogo'!$B$7:$V$41,21,0),"")) | B13: Minicraft Verde | C13: Miniatura | D13: 26 | E13: 0 | F13: 0 | G13: =IF(A13="","",D13-E13-F13) | H13: =IF(A13="","",IF(G13<0,"⚠️ NEGATIVO",IF(G13=0,"⛔ ZERADO",IF(G13<5,"📦 BAIXO","✅ OK"))))
A14: =IF(B14="","",IFERROR(VLOOKUP(B14,'📋 Catálogo'!$B$7:$V$41,21,0),"")) | B14: Pentágono Sensorial | C14: Enfeite/Decoração | D14: 23 | E14: 0 | F14: 0 | G14: =IF(A14="","",D14-E14-F14) | H14: =IF(A14="","",IF(G14<0,"⚠️ NEGATIVO",IF(G14=0,"⛔ ZERADO",IF(G14<5,"📦 BAIXO","✅ OK"))))
A15: =IF(B15="","",IFERROR(VLOOKUP(B15,'📋 Catálogo'!$B$7:$V$41,21,0),"")) | B15: Tubarão | C15: Miniatura | D15: 29 | E15: 0 | F15: 0 | G15: =IF(A15="","",D15-E15-F15) | H15: =IF(A15="","",IF(G15<0,"⚠️ NEGATIVO",IF(G15=0,"⛔ ZERADO",IF(G15<5,"📦 BAIXO","✅ OK"))))
A16: =IF(B16="","",IFERROR(VLOOKUP(B16,'📋 Catálogo'!$B$7:$V$41,21,0),"")) | B16: Nossa Senhora | C16: Miniatura | D16: 6 | E16: 0 | F16: 0 | G16: =IF(A16="","",D16-E16-F16) | H16: =IF(A16="","",IF(G16<0,"⚠️ NEGATIVO",IF(G16=0,"⛔ ZERADO",IF(G16<5,"📦 BAIXO","✅ OK"))))
... A33: =IF(B33="","",IFERROR(VLOOKUP(B33,'📋 Catálogo'!$B$7:$V$41,21,0),"")) | B33: Boca Abridor de Garrafa | C33: Plaquinha | D33: 10 | E33: 0 | F33: 0 | G33: =IF(A33="","",D33-E33-F33) | H33: =IF(A33="","",IF(G33<0,"⚠️ NEGATIVO",IF(G33=0,"⛔ ZERADO",IF(G33<5,"📦 BAIXO","✅ OK"))))
G34: =IF(A34="","",D34-E34-F34) | H34: =IF(A34="","",IF(G34<0,"⚠️ NEGATIVO",IF(G34=0,"⛔ ZERADO",IF(G34<5,"📦 BAIXO","✅ OK"))))
G35: =IF(A35="","",D35-E35-F35) | H35: =IF(A35="","",IF(G35<0,"⚠️ NEGATIVO",IF(G35=0,"⛔ ZERADO",IF(G35<5,"📦 BAIXO","✅ OK"))))
G36: =IF(A36="","",D36-E36-F36) | H36: =IF(A36="","",IF(G36<0,"⚠️ NEGATIVO",IF(G36=0,"⛔ ZERADO",IF(G36<5,"📦 BAIXO","✅ OK"))))
G37: =IF(A37="","",D37-E37-F37) | H37: =IF(A37="","",IF(G37<0,"⚠️ NEGATIVO",IF(G37=0,"⛔ ZERADO",IF(G37<5,"📦 BAIXO","✅ OK"))))
G38: =IF(A38="","",D38-E38-F38) | H38: =IF(A38="","",IF(G38<0,"⚠️ NEGATIVO",IF(G38=0,"⛔ ZERADO",IF(G38<5,"📦 BAIXO","✅ OK"))))
G39: =IF(A39="","",D39-E39-F39) | H39: =IF(A39="","",IF(G39<0,"⚠️ NEGATIVO",IF(G39=0,"⛔ ZERADO",IF(G39<5,"📦 BAIXO","✅ OK"))))
G40: =IF(A40="","",D40-E40-F40) | H40: =IF(A40="","",IF(G40<0,"⚠️ NEGATIVO",IF(G40=0,"⛔ ZERADO",IF(G40<5,"📦 BAIXO","✅ OK"))))
G41: =IF(A41="","",D41-E41-F41) | H41: =IF(A41="","",IF(G41<0,"⚠️ NEGATIVO",IF(G41=0,"⛔ ZERADO",IF(G41<5,"📦 BAIXO","✅ OK"))))
G42: =IF(A42="","",D42-E42-F42) | H42: =IF(A42="","",IF(G42<0,"⚠️ NEGATIVO",IF(G42=0,"⛔ ZERADO",IF(G42<5,"📦 BAIXO","✅ OK"))))
G43: =IF(A43="","",D43-E43-F43) | H43: =IF(A43="","",IF(G43<0,"⚠️ NEGATIVO",IF(G43=0,"⛔ ZERADO",IF(G43<5,"📦 BAIXO","✅ OK"))))
G44: =IF(A44="","",D44-E44-F44) | H44: =IF(A44="","",IF(G44<0,"⚠️ NEGATIVO",IF(G44=0,"⛔ ZERADO",IF(G44<5,"📦 BAIXO","✅ OK"))))
G45: =IF(A45="","",D45-E45-F45) | H45: =IF(A45="","",IF(G45<0,"⚠️ NEGATIVO",IF(G45=0,"⛔ ZERADO",IF(G45<5,"📦 BAIXO","✅ OK"))))
... G204: =IF(A204="","",D204-E204-F204) | H204: =IF(A204="","",IF(G204<0,"⚠️ NEGATIVO",IF(G204=0,"⛔ ZERADO",IF(G204<5,"📦 BAIXO","✅ OK"))))

Sheet 🔧 Manutenção
B1: Taldo Studio 3D · Impressão 3D Personalizada · @TaldoStudio3d · Av. Sebastião Henriques, 575
A3: 💡 Horas × R$/h de desgaste (ver Parâmetros)
A4: Mês | B4: Máquina 1 (h) | C4: Máquina 2 (h) | D4: Máquina 3 (h) | E4: Total Horas | F4: Desgaste (R$)
A5: Jan/26 | B5: 0 | C5: 0 | D5: 0 | E5: =B5+C5+D5 | F5: =E5*'⚙️ Parâmetros'!B9
A6: Fev/26 | B6: 0 | C6: 0 | D6: 0 | E6: =B6+C6+D6 | F6: =E6*'⚙️ Parâmetros'!B9
A7: Mar/26 | B7: 0 | C7: 0 | D7: 0 | E7: =B7+C7+D7 | F7: =E7*'⚙️ Parâmetros'!B9
A8: Abr/26 | B8: 0 | C8: 0 | D8: 0 | E8: =B8+C8+D8 | F8: =E8*'⚙️ Parâmetros'!B9
A9: Mai/26 | B9: 0 | C9: 0 | D9: 0 | E9: =B9+C9+D9 | F9: =E9*'⚙️ Parâmetros'!B9
A10: Jun/26 | B10: 0 | C10: 0 | D10: 0 | E10: =B10+C10+D10 | F10: =E10*'⚙️ Parâmetros'!B9
A11: Jul/26 | B11: 0 | C11: 0 | D11: 0 | E11: =B11+C11+D11 | F11: =E11*'⚙️ Parâmetros'!B9
A12: Ago/26 | B12: 0 | C12: 0 | D12: 0 | E12: =B12+C12+D12 | F12: =E12*'⚙️ Parâmetros'!B9
A13: Set/26 | B13: 0 | C13: 0 | D13: 0 | E13: =B13+C13+D13 | F13: =E13*'⚙️ Parâmetros'!B9
A14: Out/26 | B14: 0 | C14: 0 | D14: 0 | E14: =B14+C14+D14 | F14: =E14*'⚙️ Parâmetros'!B9
A15: Nov/26 | B15: 0 | C15: 0 | D15: 0 | E15: =B15+C15+D15 | F15: =E15*'⚙️ Parâmetros'!B9
A16: Dez/26 | B16: 0 | C16: 0 | D16: 0 | E16: =B16+C16+D16 | F16: =E16*'⚙️ Parâmetros'!B9
A17: TOTAL ANO | B17: =SUM(B5:B16) | C17: =SUM(C5:C16) | D17: =SUM(D5:D16) | E17: =SUM(E5:E16) | F17: =SUM(F5:F16)

Sheet 🏪 Consignados
B1: Taldo Studio 3D · Impressão 3D Personalizada · @TaldoStudio3d · Av. Sebastião Henriques, 575
A4: SKU | B4: Banca | C4: Produto | D4: Data Envio | E4: Qtd Enviada | F4: Qtd Vendida | G4: Saldo | H4: Receita (R$) | I4: Preço Unit.
G5: =IF(A5="","",E5-F5) | H5: =IF(OR(F5="",I5=""),"",F5*I5)
G6: =IF(A6="","",E6-F6) | H6: =IF(OR(F6="",I6=""),"",F6*I6)
G7: =IF(A7="","",E7-F7) | H7: =IF(OR(F7="",I7=""),"",F7*I7)
G8: =IF(A8="","",E8-F8) | H8: =IF(OR(F8="",I8=""),"",F8*I8)
G9: =IF(A9="","",E9-F9) | H9: =IF(OR(F9="",I9=""),"",F9*I9)
G10: =IF(A10="","",E10-F10) | H10: =IF(OR(F10="",I10=""),"",F10*I10)
G11: =IF(A11="","",E11-F11) | H11: =IF(OR(F11="",I11=""),"",F11*I11)
G12: =IF(A12="","",E12-F12) | H12: =IF(OR(F12="",I12=""),"",F12*I12)
G13: =IF(A13="","",E13-F13) | H13: =IF(OR(F13="",I13=""),"",F13*I13)
G14: =IF(A14="","",E14-F14) | H14: =IF(OR(F14="",I14=""),"",F14*I14)
G15: =IF(A15="","",E15-F15) | H15: =IF(OR(F15="",I15=""),"",F15*I15)
G16: =IF(A16="","",E16-F16) | H16: =IF(OR(F16="",I16=""),"",F16*I16)
... G204: =IF(A204="","",E204-F204) | H204: =IF(OR(F204="",I204=""),"",F204*I204)

Sheet 📊 Relatório
B1: Taldo Studio 3D · Impressão 3D Personalizada · @TaldoStudio3d · Av. Sebastião Henriques, 575
A4: DATA INÍCIO | B4: DATA FIM
A6: 💡 Datas em branco = mostra TODOS os pedidos entregues
A7: INDICADOR | B7: VALOR | C7: OBSERVAÇÃO
A8: 💰 Receita Bruta | B8: =IF(OR($A$5="",$B$5=""),SUMPRODUCT(('📦 Pedidos'!J5:J204="Entregue")*'📦 Pedidos'!H5:H204),SUMPRODUCT(('📦 Pedidos'!B5:B204>=$A$5)*('📦 Pedidos'!B5:B204<=$B$5)*('📦 Pedidos'!J5:J204="Entregue")*'📦 Pedidos'!H5:H204)) | C8: Pedidos entregues
A9: 📦 Pedidos Entregues | B9: =IF(OR($A$5="",$B$5=""),SUMPRODUCT(('📦 Pedidos'!J5:J204="Entregue")*1),SUMPRODUCT(('📦 Pedidos'!B5:B204>=$A$5)*('📦 Pedidos'!B5:B204<=$B$5)*('📦 Pedidos'!J5:J204="Entregue")*1)) | C9: Quantidade
A10: 🔧 Reserva Manutenção | B10: ='⚙️ Parâmetros'!B15*IF(OR($A$5="",$B$5=""),SUMPRODUCT(('📦 Pedidos'!J5:J204="Entregue")*'📦 Pedidos'!H5:H204),SUMPRODUCT(('📦 Pedidos'!B5:B204>=$A$5)*('📦 Pedidos'!B5:B204<=$B$5)*('📦 Pedidos'!J5:J204="Entregue")*'📦 Pedidos'!H5:H204)) | C10: 10% receita bruta
A11: 🏪 Receita Consignados | B11: =SUM('🏪 Consignados'!H5:H204) | C11: Acumulado bancas
A12: 📈 Receita Líquida | B12: ='📊 Relatório'!B8-'📊 Relatório'!B10 | C12: Bruta − Reserva
A13: ⚠️ Filamentos Críticos | B13: =COUNTIFS('🎨 Filamento'!$A$5:$A$400,"<>",'🎨 Filamento'!$F$5:$F$400,"<200") | C13: Abaixo de 200g
A14: 📦 Peças Estoque Baixo | B14: =COUNTIFS('📦 Est. Peças'!$A$5:$A$204,"<>",'📦 Est. Peças'!$G$5:$G$204,"<5",'📦 Est. Peças'!$G$5:$G$204,">=0") | C14: Menos de 5 unidades
A15: 🔨 Itens a Fabricar | B15: =COUNTIFS('🖨️ Produção'!$G$6:$G$205,">0") | C15: Ordens abertas

Sheet 💳 Lançamentos
A1: Taldo Studio 3D · Projeção de Parcelas — Lançamentos · v7.2
A3: 💡 Preencha: Origem, Data na Fatura (quando apareceu no cartão), Valor, Tipo, Parcelas e Parc. Atual (ex: 5 em 05/10). A coluna 'Início da Compra' calcula sozinha quantos meses atrás foi a compra. Deixe a Data em branco para usar o mês atual.
A4: # | B4: Origem | C4: Data na Fatura | D4: Descrição | E4: Cartão | F4: Valor | G4: Tipo | H4: Parcelas | I4: Parc. Atual | J4: Início da Compra | K4: Valor/Mês | L4: Total Compra | M4: Status | N4: Observações | O4: Mês Final | P4: Parc. Restantes | Q4: Validação
A5: =IF(D5="","",ROW()-4) | B5: Cartão fixo | D5: Tuelá / primeira compra - 10x R$ 499 | E5: Verde | F5: 499 | G5: Parcela mensal | H5: 10 | I5: 5 | J5: =IF(OR(I5="",H5=""),"",EDATE(DATE(YEAR(IF(C5="",TODAY(),C5)),MONTH(IF(C5="",TODAY(),C5)),1),-(I5-1))) | K5: =IF(OR(F5="",H5=""),"",IF(G5="Parcela mensal",F5,F5/H5)) | L5: =IF(OR(F5="",H5=""),"",IF(G5="Parcela mensal",F5*H5,F5)) | M5: OK | N5: Exemplo: 10x R$499, 5ª parcela → compra iniciou há 4 meses. | O5: =IF(OR(J5="",H5=""),"",EDATE(J5,H5-1)) | P5: =IF(OR(H5="",I5=""),"",H5-I5) | Q5: =IF(D5="","",IF(I5>H5,"⚠️ Parc. inválida",IF(I5<1,"⚠️ Parc. inválida","✅ Calculado")))
A6: =IF(D6="","",ROW()-4) | B6: Cartão fixo | C6: 46124 | D6: Tuelá - 02/10 de R$ 529,10 | E6: Verde | F6: 529.1 | G6: Parcela mensal | H6: 10 | I6: 2 | J6: =IF(OR(I6="",H6=""),"",EDATE(DATE(YEAR(IF(C6="",TODAY(),C6)),MONTH(IF(C6="",TODAY(),C6)),1),-(I6-1))) | K6: =IF(OR(F6="",H6=""),"",IF(G6="Parcela mensal",F6,F6/H6)) | L6: =IF(OR(F6="",H6=""),"",IF(G6="Parcela mensal",F6*H6,F6)) | M6: Cancelado | N6: DUPLICATA — mesma compra da linha 5. Uma compra = uma linha. | O6: =IF(OR(J6="",H6=""),"",EDATE(J6,H6-1)) | P6: =IF(OR(H6="",I6=""),"",H6-I6) | Q6: =IF(D6="","",IF(I6>H6,"⚠️ Parc. inválida",IF(I6<1,"⚠️ Parc. inválida","✅ Calculado")))
A7: =IF(D7="","",ROW()-4) | B7: Cartão fixo | C7: 46151 | D7: Tuelá - 03/10 de R$ 529,10 | E7: Verde | F7: 529.1 | G7: Parcela mensal | H7: 10 | I7: 3 | J7: =IF(OR(I7="",H7=""),"",EDATE(DATE(YEAR(IF(C7="",TODAY(),C7)),MONTH(IF(C7="",TODAY(),C7)),1),-(I7-1))) | K7: =IF(OR(F7="",H7=""),"",IF(G7="Parcela mensal",F7,F7/H7)) | L7: =IF(OR(F7="",H7=""),"",IF(G7="Parcela mensal",F7*H7,F7)) | M7: Cancelado | N7: DUPLICATA — excluída da projeção. | O7: =IF(OR(J7="",H7=""),"",EDATE(J7,H7-1)) | P7: =IF(OR(H7="",I7=""),"",H7-I7) | Q7: =IF(D7="","",IF(I7>H7,"⚠️ Parc. inválida",IF(I7<1,"⚠️ Parc. inválida","✅ Calculado")))
A8: =IF(D8="","",ROW()-4) | B8: TikTok | C8: 46127 | D8: Compra TikTok (descrição não legível) | E8: 9132 | F8: 145 | G8: Total da compra | H8: 3 | I8: 1 | J8: =IF(OR(I8="",H8=""),"",EDATE(DATE(YEAR(IF(C8="",TODAY(),C8)),MONTH(IF(C8="",TODAY(),C8)),1),-(I8-1))) | K8: =IF(OR(F8="",H8=""),"",IF(G8="Parcela mensal",F8,F8/H8)) | L8: =IF(OR(F8="",H8=""),"",IF(G8="Parcela mensal",F8*H8,F8)) | M8: Conferir | N8: Lido como 3x no papel. | O8: =IF(OR(J8="",H8=""),"",EDATE(J8,H8-1)) | P8: =IF(OR(H8="",I8=""),"",H8-I8) | Q8: =IF(D8="","",IF(I8>H8,"⚠️ Parc. inválida",IF(I8<1,"⚠️ Parc. inválida","✅ Calculado")))
A9: =IF(D9="","",ROW()-4) | B9: Shopee | C9: 46128 | D9: Compra Shopee | E9: 9132 | F9: 19.98 | G9: Total da compra | H9: 1 | I9: 1 | J9: =IF(OR(I9="",H9=""),"",EDATE(DATE(YEAR(IF(C9="",TODAY(),C9)),MONTH(IF(C9="",TODAY(),C9)),1),-(I9-1))) | K9: =IF(OR(F9="",H9=""),"",IF(G9="Parcela mensal",F9,F9/H9)) | L9: =IF(OR(F9="",H9=""),"",IF(G9="Parcela mensal",F9*H9,F9)) | M9: OK | O9: =IF(OR(J9="",H9=""),"",EDATE(J9,H9-1)) | P9: =IF(OR(H9="",I9=""),"",H9-I9) | Q9: =IF(D9="","",IF(I9>H9,"⚠️ Parc. inválida",IF(I9<1,"⚠️ Parc. inválida","✅ Calculado")))
A10: =IF(D10="","",ROW()-4) | B10: Shopee | C10: 46128 | D10: Compra Shopee | E10: 9132 | F10: 10.5 | G10: Total da compra | H10: 1 | I10: 1 | J10: =IF(OR(I10="",H10=""),"",EDATE(DATE(YEAR(IF(C10="",TODAY(),C10)),MONTH(IF(C10="",TODAY(),C10)),1),-(I10-1))) | K10: =IF(OR(F10="",H10=""),"",IF(G10="Parcela mensal",F10,F10/H10)) | L10: =IF(OR(F10="",H10=""),"",IF(G10="Parcela mensal",F10*H10,F10)) | M10: OK | O10: =IF(OR(J10="",H10=""),"",EDATE(J10,H10-1)) | P10: =IF(OR(H10="",I10=""),"",H10-I10) | Q10: =IF(D10="","",IF(I10>H10,"⚠️ Parc. inválida",IF(I10<1,"⚠️ Parc. inválida","✅ Calculado")))
A11: =IF(D11="","",ROW()-4) | B11: Compra digitada | C11: 46129 | D11: Café / lava roupas / pastilha | E11: 7226 | F11: 164.34 | G11: Parcela mensal | H11: 1 | I11: 1 | J11: =IF(OR(I11="",H11=""),"",EDATE(DATE(YEAR(IF(C11="",TODAY(),C11)),MONTH(IF(C11="",TODAY(),C11)),1),-(I11-1))) | K11: =IF(OR(F11="",H11=""),"",IF(G11="Parcela mensal",F11,F11/H11)) | L11: =IF(OR(F11="",H11=""),"",IF(G11="Parcela mensal",F11*H11,F11)) | M11: OK | O11: =IF(OR(J11="",H11=""),"",EDATE(J11,H11-1)) | P11: =IF(OR(H11="",I11=""),"",H11-I11) | Q11: =IF(D11="","",IF(I11>H11,"⚠️ Parc. inválida",IF(I11<1,"⚠️ Parc. inválida","✅ Calculado")))
A12: =IF(D12="","",ROW()-4) | B12: Compra digitada | C12: 46129 | D12: Filamento 2 rolos | E12: 4416 | F12: 37.84 | G12: Parcela mensal | H12: 6 | I12: 1 | J12: =IF(OR(I12="",H12=""),"",EDATE(DATE(YEAR(IF(C12="",TODAY(),C12)),MONTH(IF(C12="",TODAY(),C12)),1),-(I12-1))) | K12: =IF(OR(F12="",H12=""),"",IF(G12="Parcela mensal",F12,F12/H12)) | L12: =IF(OR(F12="",H12=""),"",IF(G12="Parcela mensal",F12*H12,F12)) | M12: OK | O12: =IF(OR(J12="",H12=""),"",EDATE(J12,H12-1)) | P12: =IF(OR(H12="",I12=""),"",H12-I12) | Q12: =IF(D12="","",IF(I12>H12,"⚠️ Parc. inválida",IF(I12<1,"⚠️ Parc. inválida","✅ Calculado")))
A13: =IF(D13="","",ROW()-4) | B13: Compra digitada | C13: 46129 | D13: Filamento 3 rolos + pacote de argola | E13: 4416 | F13: 58.93 | G13: Parcela mensal | H13: 10 | I13: 1 | J13: =IF(OR(I13="",H13=""),"",EDATE(DATE(YEAR(IF(C13="",TODAY(),C13)),MONTH(IF(C13="",TODAY(),C13)),1),-(I13-1))) | K13: =IF(OR(F13="",H13=""),"",IF(G13="Parcela mensal",F13,F13/H13)) | L13: =IF(OR(F13="",H13=""),"",IF(G13="Parcela mensal",F13*H13,F13)) | M13: OK | O13: =IF(OR(J13="",H13=""),"",EDATE(J13,H13-1)) | P13: =IF(OR(H13="",I13=""),"",H13-I13) | Q13: =IF(D13="","",IF(I13>H13,"⚠️ Parc. inválida",IF(I13<1,"⚠️ Parc. inválida","✅ Calculado")))
A14: =IF(D14="","",ROW()-4) | B14: Compra digitada | C14: 46129 | D14: Filamentos 7 rolos | E14: 4416 | F14: 90.3 | G14: Parcela mensal | H14: 10 | I14: 1 | J14: =IF(OR(I14="",H14=""),"",EDATE(DATE(YEAR(IF(C14="",TODAY(),C14)),MONTH(IF(C14="",TODAY(),C14)),1),-(I14-1))) | K14: =IF(OR(F14="",H14=""),"",IF(G14="Parcela mensal",F14,F14/H14)) | L14: =IF(OR(F14="",H14=""),"",IF(G14="Parcela mensal",F14*H14,F14)) | M14: OK | O14: =IF(OR(J14="",H14=""),"",EDATE(J14,H14-1)) | P14: =IF(OR(H14="",I14=""),"",H14-I14) | Q14: =IF(D14="","",IF(I14>H14,"⚠️ Parc. inválida",IF(I14<1,"⚠️ Parc. inválida","✅ Calculado")))
A15: =IF(D15="","",ROW()-4) | B15: Compra digitada | C15: 46129 | D15: Filamentos 8 rolos | E15: 9132 | F15: 82.27 | G15: Parcela mensal | H15: 10 | I15: 1 | J15: =IF(OR(I15="",H15=""),"",EDATE(DATE(YEAR(IF(C15="",TODAY(),C15)),MONTH(IF(C15="",TODAY(),C15)),1),-(I15-1))) | K15: =IF(OR(F15="",H15=""),"",IF(G15="Parcela mensal",F15,F15/H15)) | L15: =IF(OR(F15="",H15=""),"",IF(G15="Parcela mensal",F15*H15,F15)) | M15: OK | O15: =IF(OR(J15="",H15=""),"",EDATE(J15,H15-1)) | P15: =IF(OR(H15="",I15=""),"",H15-I15) | Q15: =IF(D15="","",IF(I15>H15,"⚠️ Parc. inválida",IF(I15<1,"⚠️ Parc. inválida","✅ Calculado")))
A16: =IF(D16="","",ROW()-4) | B16: TikTok | C16: 46129 | D16: Compra TikTok | E16: 5022 | F16: 38.71 | G16: Total da compra | H16: 5 | I16: 1 | J16: =IF(OR(I16="",H16=""),"",EDATE(DATE(YEAR(IF(C16="",TODAY(),C16)),MONTH(IF(C16="",TODAY(),C16)),1),-(I16-1))) | K16: =IF(OR(F16="",H16=""),"",IF(G16="Parcela mensal",F16,F16/H16)) | L16: =IF(OR(F16="",H16=""),"",IF(G16="Parcela mensal",F16*H16,F16)) | M16: Conferir | N16: Lido como grupo 5x no cartão 5022. | O16: =IF(OR(J16="",H16=""),"",EDATE(J16,H16-1)) | P16: =IF(OR(H16="",I16=""),"",H16-I16) | Q16: =IF(D16="","",IF(I16>H16,"⚠️ Parc. inválida",IF(I16<1,"⚠️ Parc. inválida","✅ Calculado")))
A17: =IF(D17="","",ROW()-4) | B17: TikTok | C17: 46129 | D17: Compra TikTok | E17: 5022 | F17: 23.2 | G17: Total da compra | H17: 5 | I17: 1 | J17: =IF(OR(I17="",H17=""),"",EDATE(DATE(YEAR(IF(C17="",TODAY(),C17)),MONTH(IF(C17="",TODAY(),C17)),1),-(I17-1))) | K17: =IF(OR(F17="",H17=""),"",IF(G17="Parcela mensal",F17,F17/H17)) | L17: =IF(OR(F17="",H17=""),"",IF(G17="Parcela mensal",F17*H17,F17)) | M17: Conferir | N17: Lido como grupo 5x no cartão 5022. | O17: =IF(OR(J17="",H17=""),"",EDATE(J17,H17-1)) | P17: =IF(OR(H17="",I17=""),"",H17-I17) | Q17: =IF(D17="","",IF(I17>H17,"⚠️ Parc. inválida",IF(I17<1,"⚠️ Parc. inválida","✅ Calculado")))
A18: =IF(D18="","",ROW()-4) | B18: Shopee | C18: 46130 | D18: Compra Shopee | E18: 9132 | F18: 87.33 | G18: Total da compra | H18: 4 | I18: 1 | J18: =IF(OR(I18="",H18=""),"",EDATE(DATE(YEAR(IF(C18="",TODAY(),C18)),MONTH(IF(C18="",TODAY(),C18)),1),-(I18-1))) | K18: =IF(OR(F18="",H18=""),"",IF(G18="Parcela mensal",F18,F18/H18)) | L18: =IF(OR(F18="",H18=""),"",IF(G18="Parcela mensal",F18*H18,F18)) | M18: OK | O18: =IF(OR(J18="",H18=""),"",EDATE(J18,H18-1)) | P18: =IF(OR(H18="",I18=""),"",H18-I18) | Q18: =IF(D18="","",IF(I18>H18,"⚠️ Parc. inválida",IF(I18<1,"⚠️ Parc. inválida","✅ Calculado")))
A19: =IF(D19="","",ROW()-4) | B19: Shopee | C19: 46131 | D19: Compra Shopee | E19: 9132 | F19: 38.04 | G19: Total da compra | H19: 4 | I19: 1 | J19: =IF(OR(I19="",H19=""),"",EDATE(DATE(YEAR(IF(C19="",TODAY(),C19)),MONTH(IF(C19="",TODAY(),C19)),1),-(I19-1))) | K19: =IF(OR(F19="",H19=""),"",IF(G19="Parcela mensal",F19,F19/H19)) | L19: =IF(OR(F19="",H19=""),"",IF(G19="Parcela mensal",F19*H19,F19)) | M19: OK | O19: =IF(OR(J19="",H19=""),"",EDATE(J19,H19-1)) | P19: =IF(OR(H19="",I19=""),"",H19-I19) | Q19: =IF(D19="","",IF(I19>H19,"⚠️ Parc. inválida",IF(I19<1,"⚠️ Parc. inválida","✅ Calculado")))
A20: =IF(D20="","",ROW()-4) | B20: Shopee | C20: 46131 | D20: Compra Shopee | E20: 9132 | F20: 30.87 | G20: Total da compra | H20: 4 | I20: 1 | J20: =IF(OR(I20="",H20=""),"",EDATE(DATE(YEAR(IF(C20="",TODAY(),C20)),MONTH(IF(C20="",TODAY(),C20)),1),-(I20-1))) | K20: =IF(OR(F20="",H20=""),"",IF(G20="Parcela mensal",F20,F20/H20)) | L20: =IF(OR(F20="",H20=""),"",IF(G20="Parcela mensal",F20*H20,F20)) | M20: OK | O20: =IF(OR(J20="",H20=""),"",EDATE(J20,H20-1)) | P20: =IF(OR(H20="",I20=""),"",H20-I20) | Q20: =IF(D20="","",IF(I20>H20,"⚠️ Parc. inválida",IF(I20<1,"⚠️ Parc. inválida","✅ Calculado")))
A21: =IF(D21="","",ROW()-4) | B21: Shopee | C21: 46131 | D21: Compra Shopee | E21: 9132 | F21: 75.14 | G21: Total da compra | H21: 4 | I21: 1 | J21: =IF(OR(I21="",H21=""),"",EDATE(DATE(YEAR(IF(C21="",TODAY(),C21)),MONTH(IF(C21="",TODAY(),C21)),1),-(I21-1))) | K21: =IF(OR(F21="",H21=""),"",IF(G21="Parcela mensal",F21,F21/H21)) | L21: =IF(OR(F21="",H21=""),"",IF(G21="Parcela mensal",F21*H21,F21)) | M21: OK | O21: =IF(OR(J21="",H21=""),"",EDATE(J21,H21-1)) | P21: =IF(OR(H21="",I21=""),"",H21-I21) | Q21: =IF(D21="","",IF(I21>H21,"⚠️ Parc. inválida",IF(I21<1,"⚠️ Parc. inválida","✅ Calculado")))
A22: =IF(D22="","",ROW()-4) | B22: Shopee | C22: 46131 | D22: Compra Shopee | E22: 9132 | F22: 30.33 | G22: Total da compra | H22: 4 | I22: 1 | J22: =IF(OR(I22="",H22=""),"",EDATE(DATE(YEAR(IF(C22="",TODAY(),C22)),MONTH(IF(C22="",TODAY(),C22)),1),-(I22-1))) | K22: =IF(OR(F22="",H22=""),"",IF(G22="Parcela mensal",F22,F22/H22)) | L22: =IF(OR(F22="",H22=""),"",IF(G22="Parcela mensal",F22*H22,F22)) | M22: OK | O22: =IF(OR(J22="",H22=""),"",EDATE(J22,H22-1)) | P22: =IF(OR(H22="",I22=""),"",H22-I22) | Q22: =IF(D22="","",IF(I22>H22,"⚠️ Parc. inválida",IF(I22<1,"⚠️ Parc. inválida","✅ Calculado")))
A23: =IF(D23="","",ROW()-4) | B23: TikTok | C23: 46133 | D23: Compra TikTok | E23: 4416 | F23: 458.36 | G23: Total da compra | H23: 1 | I23: 1 | J23: =IF(OR(I23="",H23=""),"",EDATE(DATE(YEAR(IF(C23="",TODAY(),C23)),MONTH(IF(C23="",TODAY(),C23)),1),-(I23-1))) | K23: =IF(OR(F23="",H23=""),"",IF(G23="Parcela mensal",F23,F23/H23)) | L23: =IF(OR(F23="",H23=""),"",IF(G23="Parcela mensal",F23*H23,F23)) | M23: Conferir | N23: Sem parcela legível; considerei 1x. | O23: =IF(OR(J23="",H23=""),"",EDATE(J23,H23-1)) | P23: =IF(OR(H23="",I23=""),"",H23-I23) | Q23: =IF(D23="","",IF(I23>H23,"⚠️ Parc. inválida",IF(I23<1,"⚠️ Parc. inválida","✅ Calculado")))
A24: =IF(D24="","",ROW()-4) | B24: Shopee | C24: 46134 | D24: Compra Shopee | E24: 7226 | F24: 43.37 | G24: Total da compra | H24: 3 | I24: 1 | J24: =IF(OR(I24="",H24=""),"",EDATE(DATE(YEAR(IF(C24="",TODAY(),C24)),MONTH(IF(C24="",TODAY(),C24)),1),-(I24-1))) | K24: =IF(OR(F24="",H24=""),"",IF(G24="Parcela mensal",F24,F24/H24)) | L24: =IF(OR(F24="",H24=""),"",IF(G24="Parcela mensal",F24*H24,F24)) | M24: OK | O24: =IF(OR(J24="",H24=""),"",EDATE(J24,H24-1)) | P24: =IF(OR(H24="",I24=""),"",H24-I24) | Q24: =IF(D24="","",IF(I24>H24,"⚠️ Parc. inválida",IF(I24<1,"⚠️ Parc. inválida","✅ Calculado")))
A25: =IF(D25="","",ROW()-4) | B25: Shopee | C25: 46134 | D25: Compra Shopee | E25: 7226 | F25: 34.03 | G25: Total da compra | H25: 3 | I25: 1 | J25: =IF(OR(I25="",H25=""),"",EDATE(DATE(YEAR(IF(C25="",TODAY(),C25)),MONTH(IF(C25="",TODAY(),C25)),1),-(I25-1))) | K25: =IF(OR(F25="",H25=""),"",IF(G25="Parcela mensal",F25,F25/H25)) | L25: =IF(OR(F25="",H25=""),"",IF(G25="Parcela mensal",F25*H25,F25)) | M25: OK | O25: =IF(OR(J25="",H25=""),"",EDATE(J25,H25-1)) | P25: =IF(OR(H25="",I25=""),"",H25-I25) | Q25: =IF(D25="","",IF(I25>H25,"⚠️ Parc. inválida",IF(I25<1,"⚠️ Parc. inválida","✅ Calculado")))
A26: =IF(D26="","",ROW()-4) | B26: Shopee | C26: 46134 | D26: Compra Shopee | E26: 7226 | F26: 14.26 | G26: Total da compra | H26: 3 | I26: 1 | J26: =IF(OR(I26="",H26=""),"",EDATE(DATE(YEAR(IF(C26="",TODAY(),C26)),MONTH(IF(C26="",TODAY(),C26)),1),-(I26-1))) | K26: =IF(OR(F26="",H26=""),"",IF(G26="Parcela mensal",F26,F26/H26)) | L26: =IF(OR(F26="",H26=""),"",IF(G26="Parcela mensal",F26*H26,F26)) | M26: Conferir | N26: Lido como 14,26 para bater com total do grupo 112,95. | O26: =IF(OR(J26="",H26=""),"",EDATE(J26,H26-1)) | P26: =IF(OR(H26="",I26=""),"",H26-I26) | Q26: =IF(D26="","",IF(I26>H26,"⚠️ Parc. inválida",IF(I26<1,"⚠️ Parc. inválida","✅ Calculado")))
A27: =IF(D27="","",ROW()-4) | B27: Shopee | C27: 46134 | D27: Compra Shopee | E27: 7226 | F27: 21.29 | G27: Total da compra | H27: 3 | I27: 1 | J27: =IF(OR(I27="",H27=""),"",EDATE(DATE(YEAR(IF(C27="",TODAY(),C27)),MONTH(IF(C27="",TODAY(),C27)),1),-(I27-1))) | K27: =IF(OR(F27="",H27=""),"",IF(G27="Parcela mensal",F27,F27/H27)) | L27: =IF(OR(F27="",H27=""),"",IF(G27="Parcela mensal",F27*H27,F27)) | M27: OK | O27: =IF(OR(J27="",H27=""),"",EDATE(J27,H27-1)) | P27: =IF(OR(H27="",I27=""),"",H27-I27) | Q27: =IF(D27="","",IF(I27>H27,"⚠️ Parc. inválida",IF(I27<1,"⚠️ Parc. inválida","✅ Calculado")))
A28: =IF(D28="","",ROW()-4) | B28: Shopee | C28: 46137 | D28: Compra Shopee | E28: 4416 | F28: 70.39 | G28: Total da compra | H28: 2 | I28: 1 | J28: =IF(OR(I28="",H28=""),"",EDATE(DATE(YEAR(IF(C28="",TODAY(),C28)),MONTH(IF(C28="",TODAY(),C28)),1),-(I28-1))) | K28: =IF(OR(F28="",H28=""),"",IF(G28="Parcela mensal",F28,F28/H28)) | L28: =IF(OR(F28="",H28=""),"",IF(G28="Parcela mensal",F28*H28,F28)) | M28: OK | O28: =IF(OR(J28="",H28=""),"",EDATE(J28,H28-1)) | P28: =IF(OR(H28="",I28=""),"",H28-I28) | Q28: =IF(D28="","",IF(I28>H28,"⚠️ Parc. inválida",IF(I28<1,"⚠️ Parc. inválida","✅ Calculado")))
A29: =IF(D29="","",ROW()-4) | B29: Shopee | C29: 46137 | D29: Compra Shopee | E29: 4416 | F29: 42.38 | G29: Total da compra | H29: 2 | I29: 1 | J29: =IF(OR(I29="",H29=""),"",EDATE(DATE(YEAR(IF(C29="",TODAY(),C29)),MONTH(IF(C29="",TODAY(),C29)),1),-(I29-1))) | K29: =IF(OR(F29="",H29=""),"",IF(G29="Parcela mensal",F29,F29/H29)) | L29: =IF(OR(F29="",H29=""),"",IF(G29="Parcela mensal",F29*H29,F29)) | M29: OK | O29: =IF(OR(J29="",H29=""),"",EDATE(J29,H29-1)) | P29: =IF(OR(H29="",I29=""),"",H29-I29) | Q29: =IF(D29="","",IF(I29>H29,"⚠️ Parc. inválida",IF(I29<1,"⚠️ Parc. inválida","✅ Calculado")))
A30: =IF(D30="","",ROW()-4) | B30: Shopee | C30: 46141 | D30: Compra Shopee | E30: 8678 NU | F30: 17.8 | G30: Total da compra | H30: 1 | I30: 1 | J30: =IF(OR(I30="",H30=""),"",EDATE(DATE(YEAR(IF(C30="",TODAY(),C30)),MONTH(IF(C30="",TODAY(),C30)),1),-(I30-1))) | K30: =IF(OR(F30="",H30=""),"",IF(G30="Parcela mensal",F30,F30/H30)) | L30: =IF(OR(F30="",H30=""),"",IF(G30="Parcela mensal",F30*H30,F30)) | M30: OK | O30: =IF(OR(J30="",H30=""),"",EDATE(J30,H30-1)) | P30: =IF(OR(H30="",I30=""),"",H30-I30) | Q30: =IF(D30="","",IF(I30>H30,"⚠️ Parc. inválida",IF(I30<1,"⚠️ Parc. inválida","✅ Calculado")))
A31: =IF(D31="","",ROW()-4) | B31: Cartão fixo | C31: 46142 | D31: Casa Touro - 01/02 | E31: Laranja | F31: 284.9 | G31: Parcela mensal | H31: 2 | I31: 1 | J31: =IF(OR(I31="",H31=""),"",EDATE(DATE(YEAR(IF(C31="",TODAY(),C31)),MONTH(IF(C31="",TODAY(),C31)),1),-(I31-1))) | K31: =IF(OR(F31="",H31=""),"",IF(G31="Parcela mensal",F31,F31/H31)) | L31: =IF(OR(F31="",H31=""),"",IF(G31="Parcela mensal",F31*H31,F31)) | M31: Conferir | N31: Lido como 01/02 de 284,90. | O31: =IF(OR(J31="",H31=""),"",EDATE(J31,H31-1)) | P31: =IF(OR(H31="",I31=""),"",H31-I31) | Q31: =IF(D31="","",IF(I31>H31,"⚠️ Parc. inválida",IF(I31<1,"⚠️ Parc. inválida","✅ Calculado")))
A32: =IF(D32="","",ROW()-4) | B32: Cartão fixo | C32: 46148 | D32: Casa Touro - 01/02 | E32: Laranja | F32: 129.95 | G32: Parcela mensal | H32: 2 | I32: 1 | J32: =IF(OR(I32="",H32=""),"",EDATE(DATE(YEAR(IF(C32="",TODAY(),C32)),MONTH(IF(C32="",TODAY(),C32)),1),-(I32-1))) | K32: =IF(OR(F32="",H32=""),"",IF(G32="Parcela mensal",F32,F32/H32)) | L32: =IF(OR(F32="",H32=""),"",IF(G32="Parcela mensal",F32*H32,F32)) | M32: Conferir | N32: Lido como 01/02 de 129,95. | O32: =IF(OR(J32="",H32=""),"",EDATE(J32,H32-1)) | P32: =IF(OR(H32="",I32=""),"",H32-I32) | Q32: =IF(D32="","",IF(I32>H32,"⚠️ Parc. inválida",IF(I32<1,"⚠️ Parc. inválida","✅ Calculado")))
A33: =IF(D33="","",ROW()-4) | B33: Shopee | C33: 46152 | D33: Compra Shopee | E33: 7226 | F33: 60 | G33: Total da compra | H33: 1 | I33: 1 | J33: =IF(OR(I33="",H33=""),"",EDATE(DATE(YEAR(IF(C33="",TODAY(),C33)),MONTH(IF(C33="",TODAY(),C33)),1),-(I33-1))) | K33: =IF(OR(F33="",H33=""),"",IF(G33="Parcela mensal",F33,F33/H33)) | L33: =IF(OR(F33="",H33=""),"",IF(G33="Parcela mensal",F33*H33,F33)) | M33: OK | O33: =IF(OR(J33="",H33=""),"",EDATE(J33,H33-1)) | P33: =IF(OR(H33="",I33=""),"",H33-I33) | Q33: =IF(D33="","",IF(I33>H33,"⚠️ Parc. inválida",IF(I33<1,"⚠️ Parc. inválida","✅ Calculado")))
A34: =IF(D34="","",ROW()-4) | B34: TikTok | C34: 46152 | D34: Compra TikTok | E34: 5022 | F34: 162.66 | G34: Total da compra | H34: 6 | I34: 1 | J34: =IF(OR(I34="",H34=""),"",EDATE(DATE(YEAR(IF(C34="",TODAY(),C34)),MONTH(IF(C34="",TODAY(),C34)),1),-(I34-1))) | K34: =IF(OR(F34="",H34=""),"",IF(G34="Parcela mensal",F34,F34/H34)) | L34: =IF(OR(F34="",H34=""),"",IF(G34="Parcela mensal",F34*H34,F34)) | M34: Conferir | N34: Lido como grupo 6x no cartão 5022. | O34: =IF(OR(J34="",H34=""),"",EDATE(J34,H34-1)) | P34: =IF(OR(H34="",I34=""),"",H34-I34) | Q34: =IF(D34="","",IF(I34>H34,"⚠️ Parc. inválida",IF(I34<1,"⚠️ Parc. inválida","✅ Calculado")))
A35: =IF(D35="","",ROW()-4) | B35: TikTok | C35: 46152 | D35: Compra TikTok | E35: 5022 | F35: 177.59 | G35: Total da compra | H35: 6 | I35: 1 | J35: =IF(OR(I35="",H35=""),"",EDATE(DATE(YEAR(IF(C35="",TODAY(),C35)),MONTH(IF(C35="",TODAY(),C35)),1),-(I35-1))) | K35: =IF(OR(F35="",H35=""),"",IF(G35="Parcela mensal",F35,F35/H35)) | L35: =IF(OR(F35="",H35=""),"",IF(G35="Parcela mensal",F35*H35,F35)) | M35: Conferir | N35: Lido como grupo 6x no cartão 5022. | O35: =IF(OR(J35="",H35=""),"",EDATE(J35,H35-1)) | P35: =IF(OR(H35="",I35=""),"",H35-I35) | Q35: =IF(D35="","",IF(I35>H35,"⚠️ Parc. inválida",IF(I35<1,"⚠️ Parc. inválida","✅ Calculado")))
A36: =IF(D36="","",ROW()-4) | B36: TikTok | C36: 46152 | D36: Compra TikTok | E36: 5022 | F36: 34 | G36: Total da compra | H36: 6 | I36: 1 | J36: =IF(OR(I36="",H36=""),"",EDATE(DATE(YEAR(IF(C36="",TODAY(),C36)),MONTH(IF(C36="",TODAY(),C36)),1),-(I36-1))) | K36: =IF(OR(F36="",H36=""),"",IF(G36="Parcela mensal",F36,F36/H36)) | L36: =IF(OR(F36="",H36=""),"",IF(G36="Parcela mensal",F36*H36,F36)) | M36: Conferir | N36: Lido como grupo 6x no cartão 5022. | O36: =IF(OR(J36="",H36=""),"",EDATE(J36,H36-1)) | P36: =IF(OR(H36="",I36=""),"",H36-I36) | Q36: =IF(D36="","",IF(I36>H36,"⚠️ Parc. inválida",IF(I36<1,"⚠️ Parc. inválida","✅ Calculado")))
A37: =IF(D37="","",ROW()-4) | B37: TikTok | C37: 46152 | D37: Compra TikTok | E37: 5022 | F37: 278.39 | G37: Total da compra | H37: 6 | I37: 1 | J37: =IF(OR(I37="",H37=""),"",EDATE(DATE(YEAR(IF(C37="",TODAY(),C37)),MONTH(IF(C37="",TODAY(),C37)),1),-(I37-1))) | K37: =IF(OR(F37="",H37=""),"",IF(G37="Parcela mensal",F37,F37/H37)) | L37: =IF(OR(F37="",H37=""),"",IF(G37="Parcela mensal",F37*H37,F37)) | M37: Conferir | N37: Lido como grupo 6x no cartão 5022. | O37: =IF(OR(J37="",H37=""),"",EDATE(J37,H37-1)) | P37: =IF(OR(H37="",I37=""),"",H37-I37) | Q37: =IF(D37="","",IF(I37>H37,"⚠️ Parc. inválida",IF(I37<1,"⚠️ Parc. inválida","✅ Calculado")))
A38: =IF(D38="","",ROW()-4) | B38: TikTok | C38: 46152 | D38: Compra TikTok | E38: 5022 | F38: 25.75 | G38: Total da compra | H38: 6 | I38: 1 | J38: =IF(OR(I38="",H38=""),"",EDATE(DATE(YEAR(IF(C38="",TODAY(),C38)),MONTH(IF(C38="",TODAY(),C38)),1),-(I38-1))) | K38: =IF(OR(F38="",H38=""),"",IF(G38="Parcela mensal",F38,F38/H38)) | L38: =IF(OR(F38="",H38=""),"",IF(G38="Parcela mensal",F38*H38,F38)) | M38: Conferir | N38: Lido como grupo 6x no cartão 5022. | O38: =IF(OR(J38="",H38=""),"",EDATE(J38,H38-1)) | P38: =IF(OR(H38="",I38=""),"",H38-I38) | Q38: =IF(D38="","",IF(I38>H38,"⚠️ Parc. inválida",IF(I38<1,"⚠️ Parc. inválida","✅ Calculado")))
A39: =IF(D39="","",ROW()-4) | B39: TikTok | C39: 46154 | D39: Compra TikTok | E39: 5022 | F39: 175.3 | G39: Total da compra | H39: 4 | I39: 1 | J39: =IF(OR(I39="",H39=""),"",EDATE(DATE(YEAR(IF(C39="",TODAY(),C39)),MONTH(IF(C39="",TODAY(),C39)),1),-(I39-1))) | K39: =IF(OR(F39="",H39=""),"",IF(G39="Parcela mensal",F39,F39/H39)) | L39: =IF(OR(F39="",H39=""),"",IF(G39="Parcela mensal",F39*H39,F39)) | M39: Conferir | N39: Lido como 4x no cartão 5022. | O39: =IF(OR(J39="",H39=""),"",EDATE(J39,H39-1)) | P39: =IF(OR(H39="",I39=""),"",H39-I39) | Q39: =IF(D39="","",IF(I39>H39,"⚠️ Parc. inválida",IF(I39<1,"⚠️ Parc. inválida","✅ Calculado")))
A40: =IF(D40="","",ROW()-4) | B40: TikTok | C40: 46155 | D40: Compra TikTok | E40: 4416 | F40: 223.34 | G40: Total da compra | H40: 1 | I40: 1 | J40: =IF(OR(I40="",H40=""),"",EDATE(DATE(YEAR(IF(C40="",TODAY(),C40)),MONTH(IF(C40="",TODAY(),C40)),1),-(I40-1))) | K40: =IF(OR(F40="",H40=""),"",IF(G40="Parcela mensal",F40,F40/H40)) | L40: =IF(OR(F40="",H40=""),"",IF(G40="Parcela mensal",F40*H40,F40)) | M40: Conferir | N40: Sem parcela legível; considerei 1x. | O40: =IF(OR(J40="",H40=""),"",EDATE(J40,H40-1)) | P40: =IF(OR(H40="",I40=""),"",H40-I40) | Q40: =IF(D40="","",IF(I40>H40,"⚠️ Parc. inválida",IF(I40<1,"⚠️ Parc. inválida","✅ Calculado")))
A41: =IF(D41="","",ROW()-4) | B41: TikTok | C41: 46159 | D41: Compra TikTok | E41: 5022 | F41: 89.92 | G41: Total da compra | H41: 1 | I41: 1 | J41: =IF(OR(I41="",H41=""),"",EDATE(DATE(YEAR(IF(C41="",TODAY(),C41)),MONTH(IF(C41="",TODAY(),C41)),1),-(I41-1))) | K41: =IF(OR(F41="",H41=""),"",IF(G41="Parcela mensal",F41,F41/H41)) | L41: =IF(OR(F41="",H41=""),"",IF(G41="Parcela mensal",F41*H41,F41)) | M41: Conferir | N41: Sem parcela legível; considerei 1x. | O41: =IF(OR(J41="",H41=""),"",EDATE(J41,H41-1)) | P41: =IF(OR(H41="",I41=""),"",H41-I41) | Q41: =IF(D41="","",IF(I41>H41,"⚠️ Parc. inválida",IF(I41<1,"⚠️ Parc. inválida","✅ Calculado")))
A42: =IF(D42="","",ROW()-4) | B42: Shopee | C42: 46161 | D42: Compra Shopee | E42: 9132 | F42: 80 | G42: Total da compra | H42: 1 | I42: 1 | J42: =IF(OR(I42="",H42=""),"",EDATE(DATE(YEAR(IF(C42="",TODAY(),C42)),MONTH(IF(C42="",TODAY(),C42)),1),-(I42-1))) | K42: =IF(OR(F42="",H42=""),"",IF(G42="Parcela mensal",F42,F42/H42)) | L42: =IF(OR(F42="",H42=""),"",IF(G42="Parcela mensal",F42*H42,F42)) | M42: OK | O42: =IF(OR(J42="",H42=""),"",EDATE(J42,H42-1)) | P42: =IF(OR(H42="",I42=""),"",H42-I42) | Q42: =IF(D42="","",IF(I42>H42,"⚠️ Parc. inválida",IF(I42<1,"⚠️ Parc. inválida","✅ Calculado")))
A43: =IF(D43="","",ROW()-4) | B43: Shopee | C43: 46161 | D43: Compra Shopee | E43: 9132 | F43: 166.97 | G43: Total da compra | H43: 6 | I43: 1 | J43: =IF(OR(I43="",H43=""),"",EDATE(DATE(YEAR(IF(C43="",TODAY(),C43)),MONTH(IF(C43="",TODAY(),C43)),1),-(I43-1))) | K43: =IF(OR(F43="",H43=""),"",IF(G43="Parcela mensal",F43,F43/H43)) | L43: =IF(OR(F43="",H43=""),"",IF(G43="Parcela mensal",F43*H43,F43)) | M43: OK | O43: =IF(OR(J43="",H43=""),"",EDATE(J43,H43-1)) | P43: =IF(OR(H43="",I43=""),"",H43-I43) | Q43: =IF(D43="","",IF(I43>H43,"⚠️ Parc. inválida",IF(I43<1,"⚠️ Parc. inválida","✅ Calculado")))
A44: =IF(D44="","",ROW()-4) | B44: Shopee | C44: 46161 | D44: Compra Shopee | E44: 9132 | F44: 139.8 | G44: Total da compra | H44: 6 | I44: 1 | J44: =IF(OR(I44="",H44=""),"",EDATE(DATE(YEAR(IF(C44="",TODAY(),C44)),MONTH(IF(C44="",TODAY(),C44)),1),-(I44-1))) | K44: =IF(OR(F44="",H44=""),"",IF(G44="Parcela mensal",F44,F44/H44)) | L44: =IF(OR(F44="",H44=""),"",IF(G44="Parcela mensal",F44*H44,F44)) | M44: Conferir | N44: Parcela lida como 6x; conferir se não é 8x. | O44: =IF(OR(J44="",H44=""),"",EDATE(J44,H44-1)) | P44: =IF(OR(H44="",I44=""),"",H44-I44) | Q44: =IF(D44="","",IF(I44>H44,"⚠️ Parc. inválida",IF(I44<1,"⚠️ Parc. inválida","✅ Calculado")))
A45: =IF(D45="","",ROW()-4) | B45: Shopee | C45: 46162 | D45: Compra Shopee | E45: 4416 | F45: 429.6 | G45: Total da compra | H45: 8 | I45: 1 | J45: =IF(OR(I45="",H45=""),"",EDATE(DATE(YEAR(IF(C45="",TODAY(),C45)),MONTH(IF(C45="",TODAY(),C45)),1),-(I45-1))) | K45: =IF(OR(F45="",H45=""),"",IF(G45="Parcela mensal",F45,F45/H45)) | L45: =IF(OR(F45="",H45=""),"",IF(G45="Parcela mensal",F45*H45,F45)) | M45: OK | O45: =IF(OR(J45="",H45=""),"",EDATE(J45,H45-1)) | P45: =IF(OR(H45="",I45=""),"",H45-I45) | Q45: =IF(D45="","",IF(I45>H45,"⚠️ Parc. inválida",IF(I45<1,"⚠️ Parc. inválida","✅ Calculado")))
A46: =IF(D46="","",ROW()-4) | B46: Cartão fixo | C46: 46164 | D46: Benhur - 01/12 | E46: Verde | F46: 441.62 | G46: Parcela mensal | H46: 12 | I46: 1 | J46: =IF(OR(I46="",H46=""),"",EDATE(DATE(YEAR(IF(C46="",TODAY(),C46)),MONTH(IF(C46="",TODAY(),C46)),1),-(I46-1))) | K46: =IF(OR(F46="",H46=""),"",IF(G46="Parcela mensal",F46,F46/H46)) | L46: =IF(OR(F46="",H46=""),"",IF(G46="Parcela mensal",F46*H46,F46)) | M46: Conferir | N46: Lido como 01/12 de 441,62. | O46: =IF(OR(J46="",H46=""),"",EDATE(J46,H46-1)) | P46: =IF(OR(H46="",I46=""),"",H46-I46) | Q46: =IF(D46="","",IF(I46>H46,"⚠️ Parc. inválida",IF(I46<1,"⚠️ Parc. inválida","✅ Calculado")))
A47: =IF(D47="","",ROW()-4) | J47: =IF(OR(I47="",H47=""),"",EDATE(DATE(YEAR(IF(C47="",TODAY(),C47)),MONTH(IF(C47="",TODAY(),C47)),1),-(I47-1))) | K47: =IF(OR(F47="",H47=""),"",IF(G47="Parcela mensal",F47,F47/H47)) | L47: =IF(OR(F47="",H47=""),"",IF(G47="Parcela mensal",F47*H47,F47)) | O47: =IF(OR(J47="",H47=""),"",EDATE(J47,H47-1)) | P47: =IF(OR(H47="",I47=""),"",H47-I47) | Q47: =IF(D47="","",IF(I47>H47,"⚠️ Parc. inválida",IF(I47<1,"⚠️ Parc. inválida","✅ Calculado")))
A48: =IF(D48="","",ROW()-4) | J48: =IF(OR(I48="",H48=""),"",EDATE(DATE(YEAR(IF(C48="",TODAY(),C48)),MONTH(IF(C48="",TODAY(),C48)),1),-(I48-1))) | K48: =IF(OR(F48="",H48=""),"",IF(G48="Parcela mensal",F48,F48/H48)) | L48: =IF(OR(F48="",H48=""),"",IF(G48="Parcela mensal",F48*H48,F48)) | O48: =IF(OR(J48="",H48=""),"",EDATE(J48,H48-1)) | P48: =IF(OR(H48="",I48=""),"",H48-I48) | Q48: =IF(D48="","",IF(I48>H48,"⚠️ Parc. inválida",IF(I48<1,"⚠️ Parc. inválida","✅ Calculado")))
A49: =IF(D49="","",ROW()-4) | J49: =IF(OR(I49="",H49=""),"",EDATE(DATE(YEAR(IF(C49="",TODAY(),C49)),MONTH(IF(C49="",TODAY(),C49)),1),-(I49-1))) | K49: =IF(OR(F49="",H49=""),"",IF(G49="Parcela mensal",F49,F49/H49)) | L49: =IF(OR(F49="",H49=""),"",IF(G49="Parcela mensal",F49*H49,F49)) | O49: =IF(OR(J49="",H49=""),"",EDATE(J49,H49-1)) | P49: =IF(OR(H49="",I49=""),"",H49-I49) | Q49: =IF(D49="","",IF(I49>H49,"⚠️ Parc. inválida",IF(I49<1,"⚠️ Parc. inválida","✅ Calculado")))
A50: =IF(D50="","",ROW()-4) | J50: =IF(OR(I50="",H50=""),"",EDATE(DATE(YEAR(IF(C50="",TODAY(),C50)),MONTH(IF(C50="",TODAY(),C50)),1),-(I50-1))) | K50: =IF(OR(F50="",H50=""),"",IF(G50="Parcela mensal",F50,F50/H50)) | L50: =IF(OR(F50="",H50=""),"",IF(G50="Parcela mensal",F50*H50,F50)) | O50: =IF(OR(J50="",H50=""),"",EDATE(J50,H50-1)) | P50: =IF(OR(H50="",I50=""),"",H50-I50) | Q50: =IF(D50="","",IF(I50>H50,"⚠️ Parc. inválida",IF(I50<1,"⚠️ Parc. inválida","✅ Calculado")))
A51: =IF(D51="","",ROW()-4) | J51: =IF(OR(I51="",H51=""),"",EDATE(DATE(YEAR(IF(C51="",TODAY(),C51)),MONTH(IF(C51="",TODAY(),C51)),1),-(I51-1))) | K51: =IF(OR(F51="",H51=""),"",IF(G51="Parcela mensal",F51,F51/H51)) | L51: =IF(OR(F51="",H51=""),"",IF(G51="Parcela mensal",F51*H51,F51)) | O51: =IF(OR(J51="",H51=""),"",EDATE(J51,H51-1)) | P51: =IF(OR(H51="",I51=""),"",H51-I51) | Q51: =IF(D51="","",IF(I51>H51,"⚠️ Parc. inválida",IF(I51<1,"⚠️ Parc. inválida","✅ Calculado")))
A52: =IF(D52="","",ROW()-4) | J52: =IF(OR(I52="",H52=""),"",EDATE(DATE(YEAR(IF(C52="",TODAY(),C52)),MONTH(IF(C52="",TODAY(),C52)),1),-(I52-1))) | K52: =IF(OR(F52="",H52=""),"",IF(G52="Parcela mensal",F52,F52/H52)) | L52: =IF(OR(F52="",H52=""),"",IF(G52="Parcela mensal",F52*H52,F52)) | O52: =IF(OR(J52="",H52=""),"",EDATE(J52,H52-1)) | P52: =IF(OR(H52="",I52=""),"",H52-I52) | Q52: =IF(D52="","",IF(I52>H52,"⚠️ Parc. inválida",IF(I52<1,"⚠️ Parc. inválida","✅ Calculado")))
A53: =IF(D53="","",ROW()-4) | J53: =IF(OR(I53="",H53=""),"",EDATE(DATE(YEAR(IF(C53="",TODAY(),C53)),MONTH(IF(C53="",TODAY(),C53)),1),-(I53-1))) | K53: =IF(OR(F53="",H53=""),"",IF(G53="Parcela mensal",F53,F53/H53)) | L53: =IF(OR(F53="",H53=""),"",IF(G53="Parcela mensal",F53*H53,F53)) | O53: =IF(OR(J53="",H53=""),"",EDATE(J53,H53-1)) | P53: =IF(OR(H53="",I53=""),"",H53-I53) | Q53: =IF(D53="","",IF(I53>H53,"⚠️ Parc. inválida",IF(I53<1,"⚠️ Parc. inválida","✅ Calculado")))
A54: =IF(D54="","",ROW()-4) | J54: =IF(OR(I54="",H54=""),"",EDATE(DATE(YEAR(IF(C54="",TODAY(),C54)),MONTH(IF(C54="",TODAY(),C54)),1),-(I54-1))) | K54: =IF(OR(F54="",H54=""),"",IF(G54="Parcela mensal",F54,F54/H54)) | L54: =IF(OR(F54="",H54=""),"",IF(G54="Parcela mensal",F54*H54,F54)) | O54: =IF(OR(J54="",H54=""),"",EDATE(J54,H54-1)) | P54: =IF(OR(H54="",I54=""),"",H54-I54) | Q54: =IF(D54="","",IF(I54>H54,"⚠️ Parc. inválida",IF(I54<1,"⚠️ Parc. inválida","✅ Calculado")))
A55: =IF(D55="","",ROW()-4) | J55: =IF(OR(I55="",H55=""),"",EDATE(DATE(YEAR(IF(C55="",TODAY(),C55)),MONTH(IF(C55="",TODAY(),C55)),1),-(I55-1))) | K55: =IF(OR(F55="",H55=""),"",IF(G55="Parcela mensal",F55,F55/H55)) | L55: =IF(OR(F55="",H55=""),"",IF(G55="Parcela mensal",F55*H55,F55)) | O55: =IF(OR(J55="",H55=""),"",EDATE(J55,H55-1)) | P55: =IF(OR(H55="",I55=""),"",H55-I55) | Q55: =IF(D55="","",IF(I55>H55,"⚠️ Parc. inválida",IF(I55<1,"⚠️ Parc. inválida","✅ Calculado")))
A56: =IF(D56="","",ROW()-4) | J56: =IF(OR(I56="",H56=""),"",EDATE(DATE(YEAR(IF(C56="",TODAY(),C56)),MONTH(IF(C56="",TODAY(),C56)),1),-(I56-1))) | K56: =IF(OR(F56="",H56=""),"",IF(G56="Parcela mensal",F56,F56/H56)) | L56: =IF(OR(F56="",H56=""),"",IF(G56="Parcela mensal",F56*H56,F56)) | O56: =IF(OR(J56="",H56=""),"",EDATE(J56,H56-1)) | P56: =IF(OR(H56="",I56=""),"",H56-I56) | Q56: =IF(D56="","",IF(I56>H56,"⚠️ Parc. inválida",IF(I56<1,"⚠️ Parc. inválida","✅ Calculado")))
A57: =IF(D57="","",ROW()-4) | J57: =IF(OR(I57="",H57=""),"",EDATE(DATE(YEAR(IF(C57="",TODAY(),C57)),MONTH(IF(C57="",TODAY(),C57)),1),-(I57-1))) | K57: =IF(OR(F57="",H57=""),"",IF(G57="Parcela mensal",F57,F57/H57)) | L57: =IF(OR(F57="",H57=""),"",IF(G57="Parcela mensal",F57*H57,F57)) | O57: =IF(OR(J57="",H57=""),"",EDATE(J57,H57-1)) | P57: =IF(OR(H57="",I57=""),"",H57-I57) | Q57: =IF(D57="","",IF(I57>H57,"⚠️ Parc. inválida",IF(I57<1,"⚠️ Parc. inválida","✅ Calculado")))
A58: =IF(D58="","",ROW()-4) | J58: =IF(OR(I58="",H58=""),"",EDATE(DATE(YEAR(IF(C58="",TODAY(),C58)),MONTH(IF(C58="",TODAY(),C58)),1),-(I58-1))) | K58: =IF(OR(F58="",H58=""),"",IF(G58="Parcela mensal",F58,F58/H58)) | L58: =IF(OR(F58="",H58=""),"",IF(G58="Parcela mensal",F58*H58,F58)) | O58: =IF(OR(J58="",H58=""),"",EDATE(J58,H58-1)) | P58: =IF(OR(H58="",I58=""),"",H58-I58) | Q58: =IF(D58="","",IF(I58>H58,"⚠️ Parc. inválida",IF(I58<1,"⚠️ Parc. inválida","✅ Calculado")))
... A96: =IF(D96="","",ROW()-4) | J96: =IF(OR(I96="",H96=""),"",EDATE(DATE(YEAR(IF(C96="",TODAY(),C96)),MONTH(IF(C96="",TODAY(),C96)),1),-(I96-1))) | K96: =IF(OR(F96="",H96=""),"",IF(G96="Parcela mensal",F96,F96/H96)) | L96: =IF(OR(F96="",H96=""),"",IF(G96="Parcela mensal",F96*H96,F96)) | O96: =IF(OR(J96="",H96=""),"",EDATE(J96,H96-1)) | P96: =IF(OR(H96="",I96=""),"",H96-I96) | Q96: =IF(D96="","",IF(I96>H96,"⚠️ Parc. inválida",IF(I96<1,"⚠️ Parc. inválida","✅ Calculado")))

Sheet 📅 Proj. Mensal
A1: Taldo Studio 3D · Projeção Mensal de Parcelas — 24 meses · v7.2
A3: Período: 24 meses | Baseado na coluna "Início da Compra" de 💳 Lançamentos
A4: Mês | B4: Total do Mês | C4: Cartão Fixo | D4: TikTok | E4: Shopee | F4: Compra Digitada | G4: Outros
A5: 46054 | B5: =SUMPRODUCT(('💳 Lançamentos'!J5:J96<=A5)*(EDATE('💳 Lançamentos'!J5:J96,'💳 Lançamentos'!H5:H96)>A5)*('💳 Lançamentos'!M5:M96<>"Cancelado")*'💳 Lançamentos'!K5:K96) | C5: =SUMPRODUCT(('💳 Lançamentos'!J5:J96<=A5)*(EDATE('💳 Lançamentos'!J5:J96,'💳 Lançamentos'!H5:H96)>A5)*('💳 Lançamentos'!M5:M96<>"Cancelado")*('💳 Lançamentos'!B5:B96="Cartão fixo")*'💳 Lançamentos'!K5:K96) | D5: =SUMPRODUCT(('💳 Lançamentos'!J5:J96<=A5)*(EDATE('💳 Lançamentos'!J5:J96,'💳 Lançamentos'!H5:H96)>A5)*('💳 Lançamentos'!M5:M96<>"Cancelado")*('💳 Lançamentos'!B5:B96="TikTok")*'💳 Lançamentos'!K5:K96) | E5: =SUMPRODUCT(('💳 Lançamentos'!J5:J96<=A5)*(EDATE('💳 Lançamentos'!J5:J96,'💳 Lançamentos'!H5:H96)>A5)*('💳 Lançamentos'!M5:M96<>"Cancelado")*('💳 Lançamentos'!B5:B96="Shopee")*'💳 Lançamentos'!K5:K96) | F5: =SUMPRODUCT(('💳 Lançamentos'!J5:J96<=A5)*(EDATE('💳 Lançamentos'!J5:J96,'💳 Lançamentos'!H5:H96)>A5)*('💳 Lançamentos'!M5:M96<>"Cancelado")*('💳 Lançamentos'!B5:B96="Compra digitada")*'💳 Lançamentos'!K5:K96) | G5: =B5-SUM(C5:F5)
A6: 46082 | B6: =SUMPRODUCT(('💳 Lançamentos'!J5:J96<=A6)*(EDATE('💳 Lançamentos'!J5:J96,'💳 Lançamentos'!H5:H96)>A6)*('💳 Lançamentos'!M5:M96<>"Cancelado")*'💳 Lançamentos'!K5:K96) | C6: =SUMPRODUCT(('💳 Lançamentos'!J5:J96<=A6)*(EDATE('💳 Lançamentos'!J5:J96,'💳 Lançamentos'!H5:H96)>A6)*('💳 Lançamentos'!M5:M96<>"Cancelado")*('💳 Lançamentos'!B5:B96="Cartão fixo")*'💳 Lançamentos'!K5:K96) | D6: =SUMPRODUCT(('💳 Lançamentos'!J5:J96<=A6)*(EDATE('💳 Lançamentos'!J5:J96,'💳 Lançamentos'!H5:H96)>A6)*('💳 Lançamentos'!M5:M96<>"Cancelado")*('💳 Lançamentos'!B5:B96="TikTok")*'💳 Lançamentos'!K5:K96) | E6: =SUMPRODUCT(('💳 Lançamentos'!J5:J96<=A6)*(EDATE('💳 Lançamentos'!J5:J96,'💳 Lançamentos'!H5:H96)>A6)*('💳 Lançamentos'!M5:M96<>"Cancelado")*('💳 Lançamentos'!B5:B96="Shopee")*'💳 Lançamentos'!K5:K96) | F6: =SUMPRODUCT(('💳 Lançamentos'!J5:J96<=A6)*(EDATE('💳 Lançamentos'!J5:J96,'💳 Lançamentos'!H5:H96)>A6)*('💳 Lançamentos'!M5:M96<>"Cancelado")*('💳 Lançamentos'!B5:B96="Compra digitada")*'💳 Lançamentos'!K5:K96) | G6: =B6-SUM(C6:F6)
A7: 46113 | B7: =SUMPRODUCT(('💳 Lançamentos'!J5:J96<=A7)*(EDATE('💳 Lançamentos'!J5:J96,'💳 Lançamentos'!H5:H96)>A7)*('💳 Lançamentos'!M5:M96<>"Cancelado")*'💳 Lançamentos'!K5:K96) | C7: =SUMPRODUCT(('💳 Lançamentos'!J5:J96<=A7)*(EDATE('💳 Lançamentos'!J5:J96,'💳 Lançamentos'!H5:H96)>A7)*('💳 Lançamentos'!M5:M96<>"Cancelado")*('💳 Lançamentos'!B5:B96="Cartão fixo")*'💳 Lançamentos'!K5:K96) | D7: =SUMPRODUCT(('💳 Lançamentos'!J5:J96<=A7)*(EDATE('💳 Lançamentos'!J5:J96,'💳 Lançamentos'!H5:H96)>A7)*('💳 Lançamentos'!M5:M96<>"Cancelado")*('💳 Lançamentos'!B5:B96="TikTok")*'💳 Lançamentos'!K5:K96) | E7: =SUMPRODUCT(('💳 Lançamentos'!J5:J96<=A7)*(EDATE('💳 Lançamentos'!J5:J96,'💳 Lançamentos'!H5:H96)>A7)*('💳 Lançamentos'!M5:M96<>"Cancelado")*('💳 Lançamentos'!B5:B96="Shopee")*'💳 Lançamentos'!K5:K96) | F7: =SUMPRODUCT(('💳 Lançamentos'!J5:J96<=A7)*(EDATE('💳 Lançamentos'!J5:J96,'💳 Lançamentos'!H5:H96)>A7)*('💳 Lançamentos'!M5:M96<>"Cancelado")*('💳 Lançamentos'!B5:B96="Compra digitada")*'💳 Lançamentos'!K5:K96) | G7: =B7-SUM(C7:F7)
A8: 46143 | B8: =SUMPRODUCT(('💳 Lançamentos'!J5:J96<=A8)*(EDATE('💳 Lançamentos'!J5:J96,'💳 Lançamentos'!H5:H96)>A8)*('💳 Lançamentos'!M5:M96<>"Cancelado")*'💳 Lançamentos'!K5:K96) | C8: =SUMPRODUCT(('💳 Lançamentos'!J5:J96<=A8)*(EDATE('💳 Lançamentos'!J5:J96,'💳 Lançamentos'!H5:H96)>A8)*('💳 Lançamentos'!M5:M96<>"Cancelado")*('💳 Lançamentos'!B5:B96="Cartão fixo")*'💳 Lançamentos'!K5:K96) | D8: =SUMPRODUCT(('💳 Lançamentos'!J5:J96<=A8)*(EDATE('💳 Lançamentos'!J5:J96,'💳 Lançamentos'!H5:H96)>A8)*('💳 Lançamentos'!M5:M96<>"Cancelado")*('💳 Lançamentos'!B5:B96="TikTok")*'💳 Lançamentos'!K5:K96) | E8: =SUMPRODUCT(('💳 Lançamentos'!J5:J96<=A8)*(EDATE('💳 Lançamentos'!J5:J96,'💳 Lançamentos'!H5:H96)>A8)*('💳 Lançamentos'!M5:M96<>"Cancelado")*('💳 Lançamentos'!B5:B96="Shopee")*'💳 Lançamentos'!K5:K96) | F8: =SUMPRODUCT(('💳 Lançamentos'!J5:J96<=A8)*(EDATE('💳 Lançamentos'!J5:J96,'💳 Lançamentos'!H5:H96)>A8)*('💳 Lançamentos'!M5:M96<>"Cancelado")*('💳 Lançamentos'!B5:B96="Compra digitada")*'💳 Lançamentos'!K5:K96) | G8: =B8-SUM(C8:F8)
A9: 46174 | B9: =SUMPRODUCT(('💳 Lançamentos'!J5:J96<=A9)*(EDATE('💳 Lançamentos'!J5:J96,'💳 Lançamentos'!H5:H96)>A9)*('💳 Lançamentos'!M5:M96<>"Cancelado")*'💳 Lançamentos'!K5:K96) | C9: =SUMPRODUCT(('💳 Lançamentos'!J5:J96<=A9)*(EDATE('💳 Lançamentos'!J5:J96,'💳 Lançamentos'!H5:H96)>A9)*('💳 Lançamentos'!M5:M96<>"Cancelado")*('💳 Lançamentos'!B5:B96="Cartão fixo")*'💳 Lançamentos'!K5:K96) | D9: =SUMPRODUCT(('💳 Lançamentos'!J5:J96<=A9)*(EDATE('💳 Lançamentos'!J5:J96,'💳 Lançamentos'!H5:H96)>A9)*('💳 Lançamentos'!M5:M96<>"Cancelado")*('💳 Lançamentos'!B5:B96="TikTok")*'💳 Lançamentos'!K5:K96) | E9: =SUMPRODUCT(('💳 Lançamentos'!J5:J96<=A9)*(EDATE('💳 Lançamentos'!J5:J96,'💳 Lançamentos'!H5:H96)>A9)*('💳 Lançamentos'!M5:M96<>"Cancelado")*('💳 Lançamentos'!B5:B96="Shopee")*'💳 Lançamentos'!K5:K96) | F9: =SUMPRODUCT(('💳 Lançamentos'!J5:J96<=A9)*(EDATE('💳 Lançamentos'!J5:J96,'💳 Lançamentos'!H5:H96)>A9)*('💳 Lançamentos'!M5:M96<>"Cancelado")*('💳 Lançamentos'!B5:B96="Compra digitada")*'💳 Lançamentos'!K5:K96) | G9: =B9-SUM(C9:F9)
A10: 46204 | B10: =SUMPRODUCT(('💳 Lançamentos'!J5:J96<=A10)*(EDATE('💳 Lançamentos'!J5:J96,'💳 Lançamentos'!H5:H96)>A10)*('💳 Lançamentos'!M5:M96<>"Cancelado")*'💳 Lançamentos'!K5:K96) | C10: =SUMPRODUCT(('💳 Lançamentos'!J5:J96<=A10)*(EDATE('💳 Lançamentos'!J5:J96,'💳 Lançamentos'!H5:H96)>A10)*('💳 Lançamentos'!M5:M96<>"Cancelado")*('💳 Lançamentos'!B5:B96="Cartão fixo")*'💳 Lançamentos'!K5:K96) | D10: =SUMPRODUCT(('💳 Lançamentos'!J5:J96<=A10)*(EDATE('💳 Lançamentos'!J5:J96,'💳 Lançamentos'!H5:H96)>A10)*('💳 Lançamentos'!M5:M96<>"Cancelado")*('💳 Lançamentos'!B5:B96="TikTok")*'💳 Lançamentos'!K5:K96) | E10: =SUMPRODUCT(('💳 Lançamentos'!J5:J96<=A10)*(EDATE('💳 Lançamentos'!J5:J96,'💳 Lançamentos'!H5:H96)>A10)*('💳 Lançamentos'!M5:M96<>"Cancelado")*('💳 Lançamentos'!B5:B96="Shopee")*'💳 Lançamentos'!K5:K96) | F10: =SUMPRODUCT(('💳 Lançamentos'!J5:J96<=A10)*(EDATE('💳 Lançamentos'!J5:J96,'💳 Lançamentos'!H5:H96)>A10)*('💳 Lançamentos'!M5:M96<>"Cancelado")*('💳 Lançamentos'!B5:B96="Compra digitada")*'💳 Lançamentos'!K5:K96) | G10: =B10-SUM(C10:F10)
A11: 46235 | B11: =SUMPRODUCT(('💳 Lançamentos'!J5:J96<=A11)*(EDATE('💳 Lançamentos'!J5:J96,'💳 Lançamentos'!H5:H96)>A11)*('💳 Lançamentos'!M5:M96<>"Cancelado")*'💳 Lançamentos'!K5:K96) | C11: =SUMPRODUCT(('💳 Lançamentos'!J5:J96<=A11)*(EDATE('💳 Lançamentos'!J5:J96,'💳 Lançamentos'!H5:H96)>A11)*('💳 Lançamentos'!M5:M96<>"Cancelado")*('💳 Lançamentos'!B5:B96="Cartão fixo")*'💳 Lançamentos'!K5:K96) | D11: =SUMPRODUCT(('💳 Lançamentos'!J5:J96<=A11)*(EDATE('💳 Lançamentos'!J5:J96,'💳 Lançamentos'!H5:H96)>A11)*('💳 Lançamentos'!M5:M96<>"Cancelado")*('💳 Lançamentos'!B5:B96="TikTok")*'💳 Lançamentos'!K5:K96) | E11: =SUMPRODUCT(('💳 Lançamentos'!J5:J96<=A11)*(EDATE('💳 Lançamentos'!J5:J96,'💳 Lançamentos'!H5:H96)>A11)*('💳 Lançamentos'!M5:M96<>"Cancelado")*('💳 Lançamentos'!B5:B96="Shopee")*'💳 Lançamentos'!K5:K96) | F11: =SUMPRODUCT(('💳 Lançamentos'!J5:J96<=A11)*(EDATE('💳 Lançamentos'!J5:J96,'💳 Lançamentos'!H5:H96)>A11)*('💳 Lançamentos'!M5:M96<>"Cancelado")*('💳 Lançamentos'!B5:B96="Compra digitada")*'💳 Lançamentos'!K5:K96) | G11: =B11-SUM(C11:F11)
A12: 46266 | B12: =SUMPRODUCT(('💳 Lançamentos'!J5:J96<=A12)*(EDATE('💳 Lançamentos'!J5:J96,'💳 Lançamentos'!H5:H96)>A12)*('💳 Lançamentos'!M5:M96<>"Cancelado")*'💳 Lançamentos'!K5:K96) | C12: =SUMPRODUCT(('💳 Lançamentos'!J5:J96<=A12)*(EDATE('💳 Lançamentos'!J5:J96,'💳 Lançamentos'!H5:H96)>A12)*('💳 Lançamentos'!M5:M96<>"Cancelado")*('💳 Lançamentos'!B5:B96="Cartão fixo")*'💳 Lançamentos'!K5:K96) | D12: =SUMPRODUCT(('💳 Lançamentos'!J5:J96<=A12)*(EDATE('💳 Lançamentos'!J5:J96,'💳 Lançamentos'!H5:H96)>A12)*('💳 Lançamentos'!M5:M96<>"Cancelado")*('💳 Lançamentos'!B5:B96="TikTok")*'💳 Lançamentos'!K5:K96) | E12: =SUMPRODUCT(('💳 Lançamentos'!J5:J96<=A12)*(EDATE('💳 Lançamentos'!J5:J96,'💳 Lançamentos'!H5:H96)>A12)*('💳 Lançamentos'!M5:M96<>"Cancelado")*('💳 Lançamentos'!B5:B96="Shopee")*'💳 Lançamentos'!K5:K96) | F12: =SUMPRODUCT(('💳 Lançamentos'!J5:J96<=A12)*(EDATE('💳 Lançamentos'!J5:J96,'💳 Lançamentos'!H5:H96)>A12)*('💳 Lançamentos'!M5:M96<>"Cancelado")*('💳 Lançamentos'!B5:B96="Compra digitada")*'💳 Lançamentos'!K5:K96) | G12: =B12-SUM(C12:F12)
A13: 46296 | B13: =SUMPRODUCT(('💳 Lançamentos'!J5:J96<=A13)*(EDATE('💳 Lançamentos'!J5:J96,'💳 Lançamentos'!H5:H96)>A13)*('💳 Lançamentos'!M5:M96<>"Cancelado")*'💳 Lançamentos'!K5:K96) | C13: =SUMPRODUCT(('💳 Lançamentos'!J5:J96<=A13)*(EDATE('💳 Lançamentos'!J5:J96,'💳 Lançamentos'!H5:H96)>A13)*('💳 Lançamentos'!M5:M96<>"Cancelado")*('💳 Lançamentos'!B5:B96="Cartão fixo")*'💳 Lançamentos'!K5:K96) | D13: =SUMPRODUCT(('💳 Lançamentos'!J5:J96<=A13)*(EDATE('💳 Lançamentos'!J5:J96,'💳 Lançamentos'!H5:H96)>A13)*('💳 Lançamentos'!M5:M96<>"Cancelado")*('💳 Lançamentos'!B5:B96="TikTok")*'💳 Lançamentos'!K5:K96) | E13: =SUMPRODUCT(('💳 Lançamentos'!J5:J96<=A13)*(EDATE('💳 Lançamentos'!J5:J96,'💳 Lançamentos'!H5:H96)>A13)*('💳 Lançamentos'!M5:M96<>"Cancelado")*('💳 Lançamentos'!B5:B96="Shopee")*'💳 Lançamentos'!K5:K96) | F13: =SUMPRODUCT(('💳 Lançamentos'!J5:J96<=A13)*(EDATE('💳 Lançamentos'!J5:J96,'💳 Lançamentos'!H5:H96)>A13)*('💳 Lançamentos'!M5:M96<>"Cancelado")*('💳 Lançamentos'!B5:B96="Compra digitada")*'💳 Lançamentos'!K5:K96) | G13: =B13-SUM(C13:F13)
A14: 46327 | B14: =SUMPRODUCT(('💳 Lançamentos'!J5:J96<=A14)*(EDATE('💳 Lançamentos'!J5:J96,'💳 Lançamentos'!H5:H96)>A14)*('💳 Lançamentos'!M5:M96<>"Cancelado")*'💳 Lançamentos'!K5:K96) | C14: =SUMPRODUCT(('💳 Lançamentos'!J5:J96<=A14)*(EDATE('💳 Lançamentos'!J5:J96,'💳 Lançamentos'!H5:H96)>A14)*('💳 Lançamentos'!M5:M96<>"Cancelado")*('💳 Lançamentos'!B5:B96="Cartão fixo")*'💳 Lançamentos'!K5:K96) | D14: =SUMPRODUCT(('💳 Lançamentos'!J5:J96<=A14)*(EDATE('💳 Lançamentos'!J5:J96,'💳 Lançamentos'!H5:H96)>A14)*('💳 Lançamentos'!M5:M96<>"Cancelado")*('💳 Lançamentos'!B5:B96="TikTok")*'💳 Lançamentos'!K5:K96) | E14: =SUMPRODUCT(('💳 Lançamentos'!J5:J96<=A14)*(EDATE('💳 Lançamentos'!J5:J96,'💳 Lançamentos'!H5:H96)>A14)*('💳 Lançamentos'!M5:M96<>"Cancelado")*('💳 Lançamentos'!B5:B96="Shopee")*'💳 Lançamentos'!K5:K96) | F14: =SUMPRODUCT(('💳 Lançamentos'!J5:J96<=A14)*(EDATE('💳 Lançamentos'!J5:J96,'💳 Lançamentos'!H5:H96)>A14)*('💳 Lançamentos'!M5:M96<>"Cancelado")*('💳 Lançamentos'!B5:B96="Compra digitada")*'💳 Lançamentos'!K5:K96) | G14: =B14-SUM(C14:F14)
A15: 46357 | B15: =SUMPRODUCT(('💳 Lançamentos'!J5:J96<=A15)*(EDATE('💳 Lançamentos'!J5:J96,'💳 Lançamentos'!H5:H96)>A15)*('💳 Lançamentos'!M5:M96<>"Cancelado")*'💳 Lançamentos'!K5:K96) | C15: =SUMPRODUCT(('💳 Lançamentos'!J5:J96<=A15)*(EDATE('💳 Lançamentos'!J5:J96,'💳 Lançamentos'!H5:H96)>A15)*('💳 Lançamentos'!M5:M96<>"Cancelado")*('💳 Lançamentos'!B5:B96="Cartão fixo")*'💳 Lançamentos'!K5:K96) | D15: =SUMPRODUCT(('💳 Lançamentos'!J5:J96<=A15)*(EDATE('💳 Lançamentos'!J5:J96,'💳 Lançamentos'!H5:H96)>A15)*('💳 Lançamentos'!M5:M96<>"Cancelado")*('💳 Lançamentos'!B5:B96="TikTok")*'💳 Lançamentos'!K5:K96) | E15: =SUMPRODUCT(('💳 Lançamentos'!J5:J96<=A15)*(EDATE('💳 Lançamentos'!J5:J96,'💳 Lançamentos'!H5:H96)>A15)*('💳 Lançamentos'!M5:M96<>"Cancelado")*('💳 Lançamentos'!B5:B96="Shopee")*'💳 Lançamentos'!K5:K96) | F15: =SUMPRODUCT(('💳 Lançamentos'!J5:J96<=A15)*(EDATE('💳 Lançamentos'!J5:J96,'💳 Lançamentos'!H5:H96)>A15)*('💳 Lançamentos'!M5:M96<>"Cancelado")*('💳 Lançamentos'!B5:B96="Compra digitada")*'💳 Lançamentos'!K5:K96) | G15: =B15-SUM(C15:F15)
A16: 46388 | B16: =SUMPRODUCT(('💳 Lançamentos'!J5:J96<=A16)*(EDATE('💳 Lançamentos'!J5:J96,'💳 Lançamentos'!H5:H96)>A16)*('💳 Lançamentos'!M5:M96<>"Cancelado")*'💳 Lançamentos'!K5:K96) | C16: =SUMPRODUCT(('💳 Lançamentos'!J5:J96<=A16)*(EDATE('💳 Lançamentos'!J5:J96,'💳 Lançamentos'!H5:H96)>A16)*('💳 Lançamentos'!M5:M96<>"Cancelado")*('💳 Lançamentos'!B5:B96="Cartão fixo")*'💳 Lançamentos'!K5:K96) | D16: =SUMPRODUCT(('💳 Lançamentos'!J5:J96<=A16)*(EDATE('💳 Lançamentos'!J5:J96,'💳 Lançamentos'!H5:H96)>A16)*('💳 Lançamentos'!M5:M96<>"Cancelado")*('💳 Lançamentos'!B5:B96="TikTok")*'💳 Lançamentos'!K5:K96) | E16: =SUMPRODUCT(('💳 Lançamentos'!J5:J96<=A16)*(EDATE('💳 Lançamentos'!J5:J96,'💳 Lançamentos'!H5:H96)>A16)*('💳 Lançamentos'!M5:M96<>"Cancelado")*('💳 Lançamentos'!B5:B96="Shopee")*'💳 Lançamentos'!K5:K96) | F16: =SUMPRODUCT(('💳 Lançamentos'!J5:J96<=A16)*(EDATE('💳 Lançamentos'!J5:J96,'💳 Lançamentos'!H5:H96)>A16)*('💳 Lançamentos'!M5:M96<>"Cancelado")*('💳 Lançamentos'!B5:B96="Compra digitada")*'💳 Lançamentos'!K5:K96) | G16: =B16-SUM(C16:F16)
A17: 46419 | B17: =SUMPRODUCT(('💳 Lançamentos'!J5:J96<=A17)*(EDATE('💳 Lançamentos'!J5:J96,'💳 Lançamentos'!H5:H96)>A17)*('💳 Lançamentos'!M5:M96<>"Cancelado")*'💳 Lançamentos'!K5:K96) | C17: =SUMPRODUCT(('💳 Lançamentos'!J5:J96<=A17)*(EDATE('💳 Lançamentos'!J5:J96,'💳 Lançamentos'!H5:H96)>A17)*('💳 Lançamentos'!M5:M96<>"Cancelado")*('💳 Lançamentos'!B5:B96="Cartão fixo")*'💳 Lançamentos'!K5:K96) | D17: =SUMPRODUCT(('💳 Lançamentos'!J5:J96<=A17)*(EDATE('💳 Lançamentos'!J5:J96,'💳 Lançamentos'!H5:H96)>A17)*('💳 Lançamentos'!M5:M96<>"Cancelado")*('💳 Lançamentos'!B5:B96="TikTok")*'💳 Lançamentos'!K5:K96) | E17: =SUMPRODUCT(('💳 Lançamentos'!J5:J96<=A17)*(EDATE('💳 Lançamentos'!J5:J96,'💳 Lançamentos'!H5:H96)>A17)*('💳 Lançamentos'!M5:M96<>"Cancelado")*('💳 Lançamentos'!B5:B96="Shopee")*'💳 Lançamentos'!K5:K96) | F17: =SUMPRODUCT(('💳 Lançamentos'!J5:J96<=A17)*(EDATE('💳 Lançamentos'!J5:J96,'💳 Lançamentos'!H5:H96)>A17)*('💳 Lançamentos'!M5:M96<>"Cancelado")*('💳 Lançamentos'!B5:B96="Compra digitada")*'💳 Lançamentos'!K5:K96) | G17: =B17-SUM(C17:F17)
A18: 46447 | B18: =SUMPRODUCT(('💳 Lançamentos'!J5:J96<=A18)*(EDATE('💳 Lançamentos'!J5:J96,'💳 Lançamentos'!H5:H96)>A18)*('💳 Lançamentos'!M5:M96<>"Cancelado")*'💳 Lançamentos'!K5:K96) | C18: =SUMPRODUCT(('💳 Lançamentos'!J5:J96<=A18)*(EDATE('💳 Lançamentos'!J5:J96,'💳 Lançamentos'!H5:H96)>A18)*('💳 Lançamentos'!M5:M96<>"Cancelado")*('💳 Lançamentos'!B5:B96="Cartão fixo")*'💳 Lançamentos'!K5:K96) | D18: =SUMPRODUCT(('💳 Lançamentos'!J5:J96<=A18)*(EDATE('💳 Lançamentos'!J5:J96,'💳 Lançamentos'!H5:H96)>A18)*('💳 Lançamentos'!M5:M96<>"Cancelado")*('💳 Lançamentos'!B5:B96="TikTok")*'💳 Lançamentos'!K5:K96) | E18: =SUMPRODUCT(('💳 Lançamentos'!J5:J96<=A18)*(EDATE('💳 Lançamentos'!J5:J96,'💳 Lançamentos'!H5:H96)>A18)*('💳 Lançamentos'!M5:M96<>"Cancelado")*('💳 Lançamentos'!B5:B96="Shopee")*'💳 Lançamentos'!K5:K96) | F18: =SUMPRODUCT(('💳 Lançamentos'!J5:J96<=A18)*(EDATE('💳 Lançamentos'!J5:J96,'💳 Lançamentos'!H5:H96)>A18)*('💳 Lançamentos'!M5:M96<>"Cancelado")*('💳 Lançamentos'!B5:B96="Compra digitada")*'💳 Lançamentos'!K5:K96) | G18: =B18-SUM(C18:F18)
A19: 46478 | B19: =SUMPRODUCT(('💳 Lançamentos'!J5:J96<=A19)*(EDATE('💳 Lançamentos'!J5:J96,'💳 Lançamentos'!H5:H96)>A19)*('💳 Lançamentos'!M5:M96<>"Cancelado")*'💳 Lançamentos'!K5:K96) | C19: =SUMPRODUCT(('💳 Lançamentos'!J5:J96<=A19)*(EDATE('💳 Lançamentos'!J5:J96,'💳 Lançamentos'!H5:H96)>A19)*('💳 Lançamentos'!M5:M96<>"Cancelado")*('💳 Lançamentos'!B5:B96="Cartão fixo")*'💳 Lançamentos'!K5:K96) | D19: =SUMPRODUCT(('💳 Lançamentos'!J5:J96<=A19)*(EDATE('💳 Lançamentos'!J5:J96,'💳 Lançamentos'!H5:H96)>A19)*('💳 Lançamentos'!M5:M96<>"Cancelado")*('💳 Lançamentos'!B5:B96="TikTok")*'💳 Lançamentos'!K5:K96) | E19: =SUMPRODUCT(('💳 Lançamentos'!J5:J96<=A19)*(EDATE('💳 Lançamentos'!J5:J96,'💳 Lançamentos'!H5:H96)>A19)*('💳 Lançamentos'!M5:M96<>"Cancelado")*('💳 Lançamentos'!B5:B96="Shopee")*'💳 Lançamentos'!K5:K96) | F19: =SUMPRODUCT(('💳 Lançamentos'!J5:J96<=A19)*(EDATE('💳 Lançamentos'!J5:J96,'💳 Lançamentos'!H5:H96)>A19)*('💳 Lançamentos'!M5:M96<>"Cancelado")*('💳 Lançamentos'!B5:B96="Compra digitada")*'💳 Lançamentos'!K5:K96) | G19: =B19-SUM(C19:F19)
A20: 46508 | B20: =SUMPRODUCT(('💳 Lançamentos'!J5:J96<=A20)*(EDATE('💳 Lançamentos'!J5:J96,'💳 Lançamentos'!H5:H96)>A20)*('💳 Lançamentos'!M5:M96<>"Cancelado")*'💳 Lançamentos'!K5:K96) | C20: =SUMPRODUCT(('💳 Lançamentos'!J5:J96<=A20)*(EDATE('💳 Lançamentos'!J5:J96,'💳 Lançamentos'!H5:H96)>A20)*('💳 Lançamentos'!M5:M96<>"Cancelado")*('💳 Lançamentos'!B5:B96="Cartão fixo")*'💳 Lançamentos'!K5:K96) | D20: =SUMPRODUCT(('💳 Lançamentos'!J5:J96<=A20)*(EDATE('💳 Lançamentos'!J5:J96,'💳 Lançamentos'!H5:H96)>A20)*('💳 Lançamentos'!M5:M96<>"Cancelado")*('💳 Lançamentos'!B5:B96="TikTok")*'💳 Lançamentos'!K5:K96) | E20: =SUMPRODUCT(('💳 Lançamentos'!J5:J96<=A20)*(EDATE('💳 Lançamentos'!J5:J96,'💳 Lançamentos'!H5:H96)>A20)*('💳 Lançamentos'!M5:M96<>"Cancelado")*('💳 Lançamentos'!B5:B96="Shopee")*'💳 Lançamentos'!K5:K96) | F20: =SUMPRODUCT(('💳 Lançamentos'!J5:J96<=A20)*(EDATE('💳 Lançamentos'!J5:J96,'💳 Lançamentos'!H5:H96)>A20)*('💳 Lançamentos'!M5:M96<>"Cancelado")*('💳 Lançamentos'!B5:B96="Compra digitada")*'💳 Lançamentos'!K5:K96) | G20: =B20-SUM(C20:F20)
A21: 46539 | B21: =SUMPRODUCT(('💳 Lançamentos'!J5:J96<=A21)*(EDATE('💳 Lançamentos'!J5:J96,'💳 Lançamentos'!H5:H96)>A21)*('💳 Lançamentos'!M5:M96<>"Cancelado")*'💳 Lançamentos'!K5:K96) | C21: =SUMPRODUCT(('💳 Lançamentos'!J5:J96<=A21)*(EDATE('💳 Lançamentos'!J5:J96,'💳 Lançamentos'!H5:H96)>A21)*('💳 Lançamentos'!M5:M96<>"Cancelado")*('💳 Lançamentos'!B5:B96="Cartão fixo")*'💳 Lançamentos'!K5:K96) | D21: =SUMPRODUCT(('💳 Lançamentos'!J5:J96<=A21)*(EDATE('💳 Lançamentos'!J5:J96,'💳 Lançamentos'!H5:H96)>A21)*('💳 Lançamentos'!M5:M96<>"Cancelado")*('💳 Lançamentos'!B5:B96="TikTok")*'💳 Lançamentos'!K5:K96) | E21: =SUMPRODUCT(('💳 Lançamentos'!J5:J96<=A21)*(EDATE('💳 Lançamentos'!J5:J96,'💳 Lançamentos'!H5:H96)>A21)*('💳 Lançamentos'!M5:M96<>"Cancelado")*('💳 Lançamentos'!B5:B96="Shopee")*'💳 Lançamentos'!K5:K96) | F21: =SUMPRODUCT(('💳 Lançamentos'!J5:J96<=A21)*(EDATE('💳 Lançamentos'!J5:J96,'💳 Lançamentos'!H5:H96)>A21)*('💳 Lançamentos'!M5:M96<>"Cancelado")*('💳 Lançamentos'!B5:B96="Compra digitada")*'💳 Lançamentos'!K5:K96) | G21: =B21-SUM(C21:F21)
A22: 46569 | B22: =SUMPRODUCT(('💳 Lançamentos'!J5:J96<=A22)*(EDATE('💳 Lançamentos'!J5:J96,'💳 Lançamentos'!H5:H96)>A22)*('💳 Lançamentos'!M5:M96<>"Cancelado")*'💳 Lançamentos'!K5:K96) | C22: =SUMPRODUCT(('💳 Lançamentos'!J5:J96<=A22)*(EDATE('💳 Lançamentos'!J5:J96,'💳 Lançamentos'!H5:H96)>A22)*('💳 Lançamentos'!M5:M96<>"Cancelado")*('💳 Lançamentos'!B5:B96="Cartão fixo")*'💳 Lançamentos'!K5:K96) | D22: =SUMPRODUCT(('💳 Lançamentos'!J5:J96<=A22)*(EDATE('💳 Lançamentos'!J5:J96,'💳 Lançamentos'!H5:H96)>A22)*('💳 Lançamentos'!M5:M96<>"Cancelado")*('💳 Lançamentos'!B5:B96="TikTok")*'💳 Lançamentos'!K5:K96) | E22: =SUMPRODUCT(('💳 Lançamentos'!J5:J96<=A22)*(EDATE('💳 Lançamentos'!J5:J96,'💳 Lançamentos'!H5:H96)>A22)*('💳 Lançamentos'!M5:M96<>"Cancelado")*('💳 Lançamentos'!B5:B96="Shopee")*'💳 Lançamentos'!K5:K96) | F22: =SUMPRODUCT(('💳 Lançamentos'!J5:J96<=A22)*(EDATE('💳 Lançamentos'!J5:J96,'💳 Lançamentos'!H5:H96)>A22)*('💳 Lançamentos'!M5:M96<>"Cancelado")*('💳 Lançamentos'!B5:B96="Compra digitada")*'💳 Lançamentos'!K5:K96) | G22: =B22-SUM(C22:F22)
A23: 46600 | B23: =SUMPRODUCT(('💳 Lançamentos'!J5:J96<=A23)*(EDATE('💳 Lançamentos'!J5:J96,'💳 Lançamentos'!H5:H96)>A23)*('💳 Lançamentos'!M5:M96<>"Cancelado")*'💳 Lançamentos'!K5:K96) | C23: =SUMPRODUCT(('💳 Lançamentos'!J5:J96<=A23)*(EDATE('💳 Lançamentos'!J5:J96,'💳 Lançamentos'!H5:H96)>A23)*('💳 Lançamentos'!M5:M96<>"Cancelado")*('💳 Lançamentos'!B5:B96="Cartão fixo")*'💳 Lançamentos'!K5:K96) | D23: =SUMPRODUCT(('💳 Lançamentos'!J5:J96<=A23)*(EDATE('💳 Lançamentos'!J5:J96,'💳 Lançamentos'!H5:H96)>A23)*('💳 Lançamentos'!M5:M96<>"Cancelado")*('💳 Lançamentos'!B5:B96="TikTok")*'💳 Lançamentos'!K5:K96) | E23: =SUMPRODUCT(('💳 Lançamentos'!J5:J96<=A23)*(EDATE('💳 Lançamentos'!J5:J96,'💳 Lançamentos'!H5:H96)>A23)*('💳 Lançamentos'!M5:M96<>"Cancelado")*('💳 Lançamentos'!B5:B96="Shopee")*'💳 Lançamentos'!K5:K96) | F23: =SUMPRODUCT(('💳 Lançamentos'!J5:J96<=A23)*(EDATE('💳 Lançamentos'!J5:J96,'💳 Lançamentos'!H5:H96)>A23)*('💳 Lançamentos'!M5:M96<>"Cancelado")*('💳 Lançamentos'!B5:B96="Compra digitada")*'💳 Lançamentos'!K5:K96) | G23: =B23-SUM(C23:F23)
A24: 46631 | B24: =SUMPRODUCT(('💳 Lançamentos'!J5:J96<=A24)*(EDATE('💳 Lançamentos'!J5:J96,'💳 Lançamentos'!H5:H96)>A24)*('💳 Lançamentos'!M5:M96<>"Cancelado")*'💳 Lançamentos'!K5:K96) | C24: =SUMPRODUCT(('💳 Lançamentos'!J5:J96<=A24)*(EDATE('💳 Lançamentos'!J5:J96,'💳 Lançamentos'!H5:H96)>A24)*('💳 Lançamentos'!M5:M96<>"Cancelado")*('💳 Lançamentos'!B5:B96="Cartão fixo")*'💳 Lançamentos'!K5:K96) | D24: =SUMPRODUCT(('💳 Lançamentos'!J5:J96<=A24)*(EDATE('💳 Lançamentos'!J5:J96,'💳 Lançamentos'!H5:H96)>A24)*('💳 Lançamentos'!M5:M96<>"Cancelado")*('💳 Lançamentos'!B5:B96="TikTok")*'💳 Lançamentos'!K5:K96) | E24: =SUMPRODUCT(('💳 Lançamentos'!J5:J96<=A24)*(EDATE('💳 Lançamentos'!J5:J96,'💳 Lançamentos'!H5:H96)>A24)*('💳 Lançamentos'!M5:M96<>"Cancelado")*('💳 Lançamentos'!B5:B96="Shopee")*'💳 Lançamentos'!K5:K96) | F24: =SUMPRODUCT(('💳 Lançamentos'!J5:J96<=A24)*(EDATE('💳 Lançamentos'!J5:J96,'💳 Lançamentos'!H5:H96)>A24)*('💳 Lançamentos'!M5:M96<>"Cancelado")*('💳 Lançamentos'!B5:B96="Compra digitada")*'💳 Lançamentos'!K5:K96) | G24: =B24-SUM(C24:F24)
A25: 46661 | B25: =SUMPRODUCT(('💳 Lançamentos'!J5:J96<=A25)*(EDATE('💳 Lançamentos'!J5:J96,'💳 Lançamentos'!H5:H96)>A25)*('💳 Lançamentos'!M5:M96<>"Cancelado")*'💳 Lançamentos'!K5:K96) | C25: =SUMPRODUCT(('💳 Lançamentos'!J5:J96<=A25)*(EDATE('💳 Lançamentos'!J5:J96,'💳 Lançamentos'!H5:H96)>A25)*('💳 Lançamentos'!M5:M96<>"Cancelado")*('💳 Lançamentos'!B5:B96="Cartão fixo")*'💳 Lançamentos'!K5:K96) | D25: =SUMPRODUCT(('💳 Lançamentos'!J5:J96<=A25)*(EDATE('💳 Lançamentos'!J5:J96,'💳 Lançamentos'!H5:H96)>A25)*('💳 Lançamentos'!M5:M96<>"Cancelado")*('💳 Lançamentos'!B5:B96="TikTok")*'💳 Lançamentos'!K5:K96) | E25: =SUMPRODUCT(('💳 Lançamentos'!J5:J96<=A25)*(EDATE('💳 Lançamentos'!J5:J96,'💳 Lançamentos'!H5:H96)>A25)*('💳 Lançamentos'!M5:M96<>"Cancelado")*('💳 Lançamentos'!B5:B96="Shopee")*'💳 Lançamentos'!K5:K96) | F25: =SUMPRODUCT(('💳 Lançamentos'!J5:J96<=A25)*(EDATE('💳 Lançamentos'!J5:J96,'💳 Lançamentos'!H5:H96)>A25)*('💳 Lançamentos'!M5:M96<>"Cancelado")*('💳 Lançamentos'!B5:B96="Compra digitada")*'💳 Lançamentos'!K5:K96) | G25: =B25-SUM(C25:F25)
A26: 46692 | B26: =SUMPRODUCT(('💳 Lançamentos'!J5:J96<=A26)*(EDATE('💳 Lançamentos'!J5:J96,'💳 Lançamentos'!H5:H96)>A26)*('💳 Lançamentos'!M5:M96<>"Cancelado")*'💳 Lançamentos'!K5:K96) | C26: =SUMPRODUCT(('💳 Lançamentos'!J5:J96<=A26)*(EDATE('💳 Lançamentos'!J5:J96,'💳 Lançamentos'!H5:H96)>A26)*('💳 Lançamentos'!M5:M96<>"Cancelado")*('💳 Lançamentos'!B5:B96="Cartão fixo")*'💳 Lançamentos'!K5:K96) | D26: =SUMPRODUCT(('💳 Lançamentos'!J5:J96<=A26)*(EDATE('💳 Lançamentos'!J5:J96,'💳 Lançamentos'!H5:H96)>A26)*('💳 Lançamentos'!M5:M96<>"Cancelado")*('💳 Lançamentos'!B5:B96="TikTok")*'💳 Lançamentos'!K5:K96) | E26: =SUMPRODUCT(('💳 Lançamentos'!J5:J96<=A26)*(EDATE('💳 Lançamentos'!J5:J96,'💳 Lançamentos'!H5:H96)>A26)*('💳 Lançamentos'!M5:M96<>"Cancelado")*('💳 Lançamentos'!B5:B96="Shopee")*'💳 Lançamentos'!K5:K96) | F26: =SUMPRODUCT(('💳 Lançamentos'!J5:J96<=A26)*(EDATE('💳 Lançamentos'!J5:J96,'💳 Lançamentos'!H5:H96)>A26)*('💳 Lançamentos'!M5:M96<>"Cancelado")*('💳 Lançamentos'!B5:B96="Compra digitada")*'💳 Lançamentos'!K5:K96) | G26: =B26-SUM(C26:F26)
A27: 46722 | B27: =SUMPRODUCT(('💳 Lançamentos'!J5:J96<=A27)*(EDATE('💳 Lançamentos'!J5:J96,'💳 Lançamentos'!H5:H96)>A27)*('💳 Lançamentos'!M5:M96<>"Cancelado")*'💳 Lançamentos'!K5:K96) | C27: =SUMPRODUCT(('💳 Lançamentos'!J5:J96<=A27)*(EDATE('💳 Lançamentos'!J5:J96,'💳 Lançamentos'!H5:H96)>A27)*('💳 Lançamentos'!M5:M96<>"Cancelado")*('💳 Lançamentos'!B5:B96="Cartão fixo")*'💳 Lançamentos'!K5:K96) | D27: =SUMPRODUCT(('💳 Lançamentos'!J5:J96<=A27)*(EDATE('💳 Lançamentos'!J5:J96,'💳 Lançamentos'!H5:H96)>A27)*('💳 Lançamentos'!M5:M96<>"Cancelado")*('💳 Lançamentos'!B5:B96="TikTok")*'💳 Lançamentos'!K5:K96) | E27: =SUMPRODUCT(('💳 Lançamentos'!J5:J96<=A27)*(EDATE('💳 Lançamentos'!J5:J96,'💳 Lançamentos'!H5:H96)>A27)*('💳 Lançamentos'!M5:M96<>"Cancelado")*('💳 Lançamentos'!B5:B96="Shopee")*'💳 Lançamentos'!K5:K96) | F27: =SUMPRODUCT(('💳 Lançamentos'!J5:J96<=A27)*(EDATE('💳 Lançamentos'!J5:J96,'💳 Lançamentos'!H5:H96)>A27)*('💳 Lançamentos'!M5:M96<>"Cancelado")*('💳 Lançamentos'!B5:B96="Compra digitada")*'💳 Lançamentos'!K5:K96) | G27: =B27-SUM(C27:F27)
A28: 46753 | B28: =SUMPRODUCT(('💳 Lançamentos'!J5:J96<=A28)*(EDATE('💳 Lançamentos'!J5:J96,'💳 Lançamentos'!H5:H96)>A28)*('💳 Lançamentos'!M5:M96<>"Cancelado")*'💳 Lançamentos'!K5:K96) | C28: =SUMPRODUCT(('💳 Lançamentos'!J5:J96<=A28)*(EDATE('💳 Lançamentos'!J5:J96,'💳 Lançamentos'!H5:H96)>A28)*('💳 Lançamentos'!M5:M96<>"Cancelado")*('💳 Lançamentos'!B5:B96="Cartão fixo")*'💳 Lançamentos'!K5:K96) | D28: =SUMPRODUCT(('💳 Lançamentos'!J5:J96<=A28)*(EDATE('💳 Lançamentos'!J5:J96,'💳 Lançamentos'!H5:H96)>A28)*('💳 Lançamentos'!M5:M96<>"Cancelado")*('💳 Lançamentos'!B5:B96="TikTok")*'💳 Lançamentos'!K5:K96) | E28: =SUMPRODUCT(('💳 Lançamentos'!J5:J96<=A28)*(EDATE('💳 Lançamentos'!J5:J96,'💳 Lançamentos'!H5:H96)>A28)*('💳 Lançamentos'!M5:M96<>"Cancelado")*('💳 Lançamentos'!B5:B96="Shopee")*'💳 Lançamentos'!K5:K96) | F28: =SUMPRODUCT(('💳 Lançamentos'!J5:J96<=A28)*(EDATE('💳 Lançamentos'!J5:J96,'💳 Lançamentos'!H5:H96)>A28)*('💳 Lançamentos'!M5:M96<>"Cancelado")*('💳 Lançamentos'!B5:B96="Compra digitada")*'💳 Lançamentos'!K5:K96) | G28: =B28-SUM(C28:F28)
A29: TOTAL 24 MESES | B29: =SUM(B5:B28) | C29: =SUM(C5:C28) | D29: =SUM(D5:D28) | E29: =SUM(E5:E28) | F29: =SUM(F5:F28) | G29: =SUM(G5:G28)

Sheet 📊 Resumo Parcelas
A1: Taldo Studio 3D · Resumo da Projeção de Parcelas · v7.2
A3: INDICADOR | B3: VALOR
A4: 📅 Mês inicial | B4: =MINIFS('💳 Lançamentos'!J5:J96,'💳 Lançamentos'!J5:J96,">0")
A5: 📅 Mês final | B5: =MAXIFS('💳 Lançamentos'!O5:O96,'💳 Lançamentos'!O5:O96,">0")
A6: 💰 Total projetado 24m | B6: =SUM('📅 Proj. Mensal'!B5:B28)
A7: 📦 Qtd lançamentos | B7: =COUNTA('💳 Lançamentos'!D5:D96)
A8: ⚠️ Itens para conferir | B8: =COUNTIF('💳 Lançamentos'!M5:M96,"Conferir")
A9: 📈 Maior mês | B9: =MAX('📅 Proj. Mensal'!B5:B28)
A10: 📉 Menor mês | B10: =MINIFS('📅 Proj. Mensal'!B5:B28,'📅 Proj. Mensal'!B5:B28,">0")
A11: 📊 Média mensal | B11: =AVERAGE('📅 Proj. Mensal'!B5:B28)
A14: 📋 COMO USAR
A15: 1. Em 💳 Lançamentos: informe a Parc. Atual (ex: 5 se aparece 05/10 na fatura).
A16: 2. Data na Fatura = dia que a parcela apareceu no cartão. Em branco = usa mês atual.
A17: 3. Início da Compra calcula automaticamente: se está na 5ª de 10, a compra foi há 4 meses.
A18: 4. A aba 📅 Proj. Mensal atualiza sozinha com base no Início da Compra.
A19: 5. Itens "Conferir" no Status precisam de validação manual nas observações.
A20: 6. Para nova compra: adicione uma linha em 💳 Lançamentos.
